<?xml version="1.0" encoding="UTF-8" ?>
<!-- Created from PDF via Acrobat SaveAsXML -->
<!-- Mapping Table version: 28-February-2003 -->
<TaggedPDF-doc>
<?xpacket begin='﻿' id='W5M0MpCehiHzreSzNTczkc9d'?>
<?xpacket begin="﻿" id="W5M0MpCehiHzreSzNTczkc9d"?>
<x:xmpmeta xmlns:x="adobe:ns:meta/" x:xmptk="Adobe XMP Core 5.4-c005 78.147326, 2012/08/23-13:03:03        ">
   <rdf:RDF xmlns:rdf="http://www.w3.org/1999/02/22-rdf-syntax-ns#">
      <rdf:Description rdf:about=""
            xmlns:xmp="http://ns.adobe.com/xap/1.0/"
            xmlns:xmpMM="http://ns.adobe.com/xap/1.0/mm/"
            xmlns:dc="http://purl.org/dc/elements/1.1/"
            xmlns:pdf="http://ns.adobe.com/pdf/1.3/">
         <xmp:ModifyDate>2007-10-25T16:13:50+08:00</xmp:ModifyDate>
         <xmp:CreateDate>2007-10-25T16:13:19+08:00</xmp:CreateDate>
         <xmp:MetadataDate>2007-10-25T16:13:50+08:00</xmp:MetadataDate>
         <xmpMM:DocumentID>uuid:59c4f319-0770-4825-8dbb-6ce6c529392e</xmpMM:DocumentID>
         <xmpMM:InstanceID>uuid:c199b68d-673f-457f-9af1-4b99f1c83524</xmpMM:InstanceID>
         <dc:format>xml</dc:format>
         <pdf:Producer>Adobe Acrobat Pro 11.0.0 Paper Capture Plug-in</pdf:Producer>
      </rdf:Description>
   </rdf:RDF>
</x:xmpmeta>
                                                                                                    
                                                                                                    
                                                                                                    
                                                                                                    
                                                                                                    
                                                                                                    
                                                                                                    
                                                                                                    
                                                                                                    
                                                                                                    
                                                                                                    
                                                                                                    
                                                                                                    
                                                                                                    
                                                                                                    
                                                                                                    
                                                                                                    
                                                                                                    
                                                                                                    
                                                                                                    
                           
<?xpacket end="w"?>
<?xpacket end='r'?>

<P>臼以凹的七tl</P>

<P>員</P>

<P>財產</P>

<P>申</P>

<P>么?</P>

<P>職</P>

<P>報表</P>

<Part>
<H2>人</H2>

<P>土地坐落面積權利範園(持分)所有權人(平方公尺)</P>

<Table>
<TR>
<TH>申報人姓名</TH>

<TH>責玲挪</TH>

<TH>服務機關</TH>

<TH>1.國民大會2. </TH>

<TH/>

<TH>職稱 </TH>

<TH>1.國大代表2. </TH>
</TR>

<TR>
<TD>商己偶</TD>

<TD>及未成年子</TD>

<TD>女</TD>

<TD>商己偶及</TD>

<TD>未成</TD>

<TD>年子女</TD>
</TR>

<TR>
<TD>稱</TD>

<TD>謂</TD>

<TD>姓</TD>

<TD>名</TD>

<TD>幸存</TD>

<TD>謂</TD>

<TD>姓</TD>

<TD>名</TD>
</TR>

<TR>
<TD>配偶</TD>

<TD/>

<TD>張贊讓</TD>

<TD/>

<TD>長子</TD>

<TD/>

<TD>張惟環</TD>

<TD/>
</TR>

<TR>
<TD>長女</TD>

<TD/>

<TD>張惟絮</TD>

<TD/>

<TD/>

<TD/>

<TD/>

<TD/>
</TR>
</Table>

<P>(一)不動產</P>

<P>l.土地</P>

<P>宜蘭縣五結鄉四結段。546一0001地號 24.84 所有權全部 張贊欒</P>

<P>2.房屋</P>

<P>示</P>

<P>中票</P>

<P>面積權利範園(持分)</P>

<P>房屋</P>

<P>所有權人</P>

<P>(平方公尺)</P>

<P>無</P>

<P>(二)船身自 </P>

<P>總</P>

<P>亦祠，</P>
</Part>

<Part>
<H1>i FH</H1>

<P>港</P>

<P>船數</P>

<P>色，</P>

<P>EJ</P>

<P>種類汽缸容量牌p.~ 號碼戶斤有人</P>

<P>小白客1, 580cc IQ-3803 張贊梁 </P>

<Sect>
<H1>--土豆
</H1>

<Sect>
<P>籍</P>
</Sect>

<P>，何，</P>

<Sect>
<P>噸</P>
</Sect>

<P>(三)汽車</P>

<P>(四)航空器</P>

<P>型式製造廠名幸存國籍標示及編號所有人無</P>

<P>(五)存款(總金額:121, 928 元)</P>

<Sect>
<P>l.新臺幣存款</P>
</Sect>

<Table>
<TR>
<TD>種</TD>

<TD>類</TD>

<TD>存</TD>

<TD>放</TD>

<TD>機</TD>

<TD>構</TD>

<TD>尸</TD>

<TD>名</TD>

<TD>金</TD>

<TD>額</TD>
</TR>

<TR>
<TD>活儲</TD>

<TD/>

<TD>台灣中小企銀</TD>

<TD/>

<TD/>

<TD>黃玲娜 </TD>

<TD/>

<TD>110, 641 </TD>
</TR>

<TR>
<TD>活儲</TD>

<TD/>

<TD>彰化銀行</TD>

<TD/>

<TD/>

<TD>黃玲娜 </TD>

<TD/>

<TD>8, 386 </TD>
</TR>

<TR>
<TD>活儲</TD>

<TD/>

<TD>台灣銀行</TD>

<TD/>

<TD/>

<TD>:叫irf仰</TD>

<TD>~ </TD>

<TD>751 i </TD>
</TR>

<TR>
<TD>活儲</TD>

<TD/>

<TD>(會七銀行</TD>

<TD/>

<TD/>

<TD>賣掉眼線站</TD>

<TD>{左 </TD>

<TD>2, 150 I </TD>
</TR>
</Table>

<P>監察院公報公職人員財產申報資料專刊</P>

<P>第十八期</P>

<P>四七一八</P>

<Sect>
<P>X~ 
</P>

<P>2.外幣及其他幣別存款</P>
</Sect>

<P>放機 ~ 新合新壘幣價輯</P>

<P>(六)外幣(指現金或旅行支票)(總價額:元)</P>

<P>|幣別|所有人|金額|折合新臺幣價額|</P>

<Sect>
<P>|無 I I </P>
</Sect>

<P>(七)有價證券(股票、票券、債券及其他有價證券總價額</P>

<Table>
<TR>
<TH>1.股票(總價額:</TH>

<TH>側， 000</TH>

<TH>元)</TH>
</TR>

<TR>
<TD>種 </TD>

<TD>類</TD>

<TD>所有</TD>

<TD>人</TD>

<TD>股</TD>

<TD>數</TD>

<TD>票面價額</TD>

<TD>總</TD>

<TD>額</TD>
</TR>

<TR>
<TD>台新國際商業銀行</TD>

<TD/>

<TD>黃玲娜</TD>

<TD/>

<TD/>

<TD>8, 000 </TD>

<TD>10 </TD>

<TD/>

<TD>80, 000 </TD>
</TR>
</Table>

<Sect>
<P>有</P>
</Sect>
</Sect>

<Sect>
<Sect>
<H1>人巨型</H1>

<P>正
</P>

<P>有</P>
</Sect>

<Sect>
<Sect>
<H1>人閉</H1>
</Sect>

<P>產種類有</P>
</Sect>

<Sect>
<Sect>
<H1>值</H1>
</Sect>

<P>2, 310, 000 元)</P>

<Table>
<TR>
<TD>種</TD>

<TD>類</TD>

<TD>債權人</TD>

<TD>債務人及 </TD>

<TD>t也 </TD>

<TD>hl </TD>

<TD>金</TD>

<TD>額</TD>
</TR>

<TR>
<TD>借貸</TD>

<TD/>

<TD>黃玲娜</TD>

<TD>永宜春蘭木市新行興路22-6號 </TD>

<TD/>

<TD/>

<TD/>

<TD>710， 00。</TD>
</TR>

<TR>
<TD>借貸</TD>

<TD/>

<TD>張贊梁</TD>

<TD>進宜興蘭營市造進士有路限公15司l巷5弄1號 </TD>

<TD/>

<TD/>

<TD/>

<TD>1, 600, 000 </TD>
</TR>
</Table>

<P>(十)債務(總金額:元)</P>

<Sect>
<P>(豆類|憤務</P>
</Sect>

<P>權人及主也</P>

<Sect>
<P>吽刊</P>

<P>、 </P>

<P>p'</P>

<P>類</P>

<P>額額價價總總</P>

<P>券券票一一債</P>

<P>。'，缸闖一 </P>
</Sect>
</Sect>

<Sect>
<H1>吋土</H1>

<Sect>
<P>-nd</P>

<P>有</P>
</Sect>

<Sect>
<Sect>
<H1>人哲</H1>
</Sect>

<P>監察院公報公職人員財產申報資料專刊</P>

<P>一種一無一</P>

<P>第十八期</P>

<P>所類價人</P>

<P>金</P>

<P>止</P>

<P>，吋』'</P>

<P>債</P>

<P>人</P>

<P>四七一九</P>

<Sect>
<P>|無|</P>

<P>x</P>
</Sect>

<P><Figure>

<ImageData src=""/>
</Figure>
t母事業投資(總金額:1, 500, 000 元) </P>

<P>.地</P>

<P>技;資人資事業.t; 稱 及起k投實金頻 </P>

<P>黃玲娜營造有限公司1, 500, 000 </P>

<Sect>
<P>蘭市進士路151巷5弄1號</P>
</Sect>
</Sect>

<Sect>
<H1>力且 
</H1>

<P>的備註</P>

<Table>
<TR>
<TH>1 .申報人之配偶張贊東原任職於台灣中興紙業公司，曾申購員工住宅一戶，目前正興建中， 尚未完工交屋，惟已繳款新台幣伍拾梁萬伍仟元正。土地雖已辦理完成所有權移轉，惟仍未取|得權狀，故財產申報土地欄中所填資料係根據宜蘭縣稅捐處所發出之地價稅單。 </TH>
</TR>

<TR>
<TH>2.申報人與配偶財產總額較去年度增加，係因張贊東年中自中興紙業公司辦理優惠資連，領</TH>
</TR>

<TR>
<TH>取壹佰貳拾萬參仟肆佰伍拾捌元資遣費。 </TH>
</TR>

<TR>
<TH>3.張贊梁原羅東郵局活儲帳戶，轉由兄長張贊益使用作為代繳各頃費用之用，戶名雖不變，</TH>
</TR>

<TR>
<TH>惟已非張贊梁之財產。</TH>
</TR>
</Table>

<Sect>
<P>此致監察院</P>

<P>(受理申報機關〔構〕全稱)</P>
</Sect>

<P>以上資料，本人係依法誠實申報，如有不實，願負法律責任。</P>

<P>申報人:黃玲娜申報日期: 83年 12月 31日</P>

<P>F J </P>

<P>O </P>

<P>監察院公報公職人員財產申報資料專刊 第十八期</P>

<P>四七二 </P>

<P>的“</P>
</Sect>
</Sect>
</Sect>
</Part>
</TaggedPDF-doc>
