<?xml version="1.0" encoding="UTF-8" ?>
<!-- Created from PDF via Acrobat SaveAsXML -->
<!-- Mapping Table version: 28-February-2003 -->
<TaggedPDF-doc>
<?xpacket begin='﻿' id='W5M0MpCehiHzreSzNTczkc9d'?>
<?xpacket begin="﻿" id="W5M0MpCehiHzreSzNTczkc9d"?>
<x:xmpmeta xmlns:x="adobe:ns:meta/" x:xmptk="Adobe XMP Core 5.4-c005 78.147326, 2012/08/23-13:03:03        ">
   <rdf:RDF xmlns:rdf="http://www.w3.org/1999/02/22-rdf-syntax-ns#">
      <rdf:Description rdf:about=""
            xmlns:xmp="http://ns.adobe.com/xap/1.0/"
            xmlns:xmpMM="http://ns.adobe.com/xap/1.0/mm/"
            xmlns:dc="http://purl.org/dc/elements/1.1/"
            xmlns:pdf="http://ns.adobe.com/pdf/1.3/">
         <xmp:ModifyDate>2007-10-25T16:17:40+08:00</xmp:ModifyDate>
         <xmp:CreateDate>2007-10-25T16:17:29+08:00</xmp:CreateDate>
         <xmp:MetadataDate>2007-10-25T16:17:40+08:00</xmp:MetadataDate>
         <xmpMM:DocumentID>uuid:d93c909d-5c04-4783-9dca-5054a79e2d09</xmpMM:DocumentID>
         <xmpMM:InstanceID>uuid:52a8f474-33ff-4cb0-97d7-66596e090e23</xmpMM:InstanceID>
         <dc:format>xml</dc:format>
         <pdf:Producer>Adobe Acrobat Pro 11.0.0 Paper Capture Plug-in</pdf:Producer>
      </rdf:Description>
   </rdf:RDF>
</x:xmpmeta>
                                                                                                    
                                                                                                    
                                                                                                    
                                                                                                    
                                                                                                    
                                                                                                    
                                                                                                    
                                                                                                    
                                                                                                    
                                                                                                    
                                                                                                    
                                                                                                    
                                                                                                    
                                                                                                    
                                                                                                    
                                                                                                    
                                                                                                    
                                                                                                    
                                                                                                    
                                                                                                    
                           
<?xpacket end="w"?>
<?xpacket end='r'?>

<P>公職</P>

<P>員財產</P>

<P>申</P>

<P>報表</P>

<P>再</P>

<P>H!</P>

<Table>
<TR>
<TH>申報人姓名</TH>

<TH>許新枝</TH>

<TH>服務機關</TH>

<TH>1.監察院</TH>

<TH/>

<TH>職稱 </TH>

<TH>1.監察委員2.</TH>
</TR>

<TR>
<TD>2. </TD>

<TD/>
</TR>

<TR>
<TH>商己偽</TH>

<TD>及未成年三字</TD>

<TD>女</TD>

<TD>商己偶及</TD>

<TD>未成年子女</TD>
</TR>

<TR>
<TH>幸存</TH>

<TD>謂</TD>

<TD>姓</TD>

<TD>名</TD>

<TD>稱</TD>

<TD>謂</TD>

<TD>宜生 _,t </TD>
</TR>

<TR>
<TH>妻</TH>

<TD/>

<TD>蘇淑瞳</TD>

<TD/>

<TD/>

<TD/>

<TD/>
</TR>
</Table>

<P>(一)不動產</P>

<L>
<LI>
<Lbl>1.</Lbl>

<LBody>土地</LBody>
</LI>

<LI>
<Lbl>2.</Lbl>

<LBody>房屋</LBody>
</LI>
</L>

<Table>
<TR>
<TH>土地坐落</TH>

<TH>(面平方公尺積) </TH>

<TH>權利範園(持分)</TH>

<TH>所有權人 l</TH>
</TR>

<TR>
<TH>建台北市北投文林段3小段947-2， 956， 957，地目: </TH>

<TD>805 </TD>

<TD>3分之l</TD>

<TD>蘇淑瞳</TD>
</TR>

<TR>
<TH>台北市北投文林段3小段948，地目:建 </TH>

<TD>85 </TD>

<TD>所有權全部</TD>

<TD>蘇淑瞳</TD>
</TR>

<TR>
<TH>跳圖市東國段125，地目:建 </TH>

<TD>341 </TD>

<TD>10000分之3806</TD>

<TD>蘇淑瞳</TD>
</TR>

<TR>
<TH>桃園市大槽溪段335一1，地目:早 </TH>

<TD>1, 243 </TD>

<TD>80分之間</TD>

<TD>蘇淑瞳</TD>
</TR>

<TR>
<TH>被圍市大槽溪段356，地目:回 </TH>

<TD>2, 560 </TD>

<TD>80分之間</TD>

<TD>蘇淑幢</TD>
</TR>

<TR>
<TH>桃地園目市:道大槽溪段367寸， -2，一 3，一 5， -7，一 15，一鈍， </TH>

<TD>2, 247 </TD>

<TD>200分之20</TD>

<TD>蘇淑愷</TD>
</TR>

<TR>
<TH>桃目園:溜縣八德鄉大滴段11 02, 1103, 1104, 1122，地 </TH>

<TD>19, 288 </TD>

<TD>10000分之1643</TD>

<TD>蘇激瞳</TD>
</TR>

<TR>
<TH>桃園縣八德鄉大滴段454， 455，地目:溜 </TH>

<TD>43, 736 </TD>

<TD>6000分之260</TD>

<TD>蘇淑瞳</TD>
</TR>

<TR>
<TH>桃園縣觀音鄉草漂段346， 346-6，地目:回 </TH>

<TD>10, 362 </TD>

<TD>6分之2</TD>

<TD>蘇淑幢 </TD>
</TR>
</Table>

<Table>
<TR>
<TH>房屋</TH>

<TH>標</TH>

<TH>可T</TH>

<TH>(面平方公尺積) </TH>

<TH>權利範園(持分)</TH>

<TH>所有權人</TH>
</TR>

<TR>
<TD>台北市北投區明德路21號 </TD>

<TD/>

<TD/>

<TD>251 </TD>

<TD>3分之l</TD>

<TD>蘇淑鎧</TD>
</TR>

<TR>
<TD>桃園市忠孝街28， 30號 </TD>

<TD/>

<TD/>

<TD>152 </TD>

<TD>所有權全部</TD>

<TD>蘇淑瞳</TD>
</TR>

<TR>
<TD>跳圖市忠孝街28一1， 30-1號 </TD>

<TD/>

<TD/>

<TD>147 </TD>

<TD>所有權全部</TD>

<TD>蘇淑瞳</TD>
</TR>
</Table>

<P>F
</P>

<P>總類</P>

<P>4頁</P>

<P>船數</P>

<P>籍</P>

<P>港</P>

<P>、餌，</P>

<P>有</P>

<P>監察院公報公職人員財產申報資料專刊第+九期五一七六</P>

<P>E一</P>

<Part>
<H2>人</H2>

<P>缸</P>

<P>容 </P>

<P>量</P>

<P>牌</P>

<P>JHl，、</P>

<P>號</P>

<P>碼</P>

<P>有</P>
</Part>

<Part>
<H2>l空</H2>

<P>製 造廠名稱‘ i國籍標示及編號|所有</P>

<P>|無|</P>

<P>1,070,958 元)</P>

<Table>
<TR>
<TD>種類活儲</TD>

<TD>存放機構華信銀行</TD>

<TD>戶名許新枝 </TD>

<TD>金</TD>

<TD>388,429 I </TD>
</TR>

<TR>
<TD>活儲</TD>

<TD>台灣中小企業銀行</TD>

<TD>許新校 </TD>

<TD/>

<TD>40,425 </TD>
</TR>

<TR>
<TD>郵政儲金</TD>

<TD>郵局</TD>

<TD>許新校 </TD>

<TD/>

<TD>440 ,707 </TD>
</TR>

<TR>
<TD>郵政儲金</TD>

<TD>郵局</TD>

<TD>蘇淑瞳 </TD>

<TD/>

<TD>74,375 </TD>
</TR>

<TR>
<TD>活儲</TD>

<TD>第一銀行</TD>

<TD>蘇淑瞳 </TD>

<TD/>

<TD>32,945 </TD>
</TR>

<TR>
<TD>活儲</TD>

<TD>彰化銀行</TD>

<TD>蘇淑瞳 </TD>

<TD/>

<TD>9,546 </TD>
</TR>

<TR>
<TD>活儲</TD>

<TD>台灣中小企銀</TD>

<TD>蘇淑瞳 </TD>

<TD/>

<TD>37,041 </TD>
</TR>

<TR>
<TD>活儲</TD>

<TD>上海商業儲蓄銀行</TD>

<TD>蘇淑瞳 </TD>

<TD/>

<TD>3,703 </TD>
</TR>

<TR>
<TD>活儲</TD>

<TD>桃園市信用合作社</TD>

<TD>蘇淑瞳 </TD>

<TD/>

<TD>43,787 </TD>
</TR>
</Table>

<P>監察院公報公職人員財產申報資料專刊</P>

<P>軍</P>

<P>九期</P>

<P>2.外幣及其他幣別存款</P>

<P>別</P>

<P>構</P>

<P>lhγi1l</P>

<Sect>
<H2>|種類|瞥別|存名|金額 1 </H2>

<P>放機</P>

<P>|無 I I |! </P>

<P>(六)外幣(指現金或旅行支票)(總價額:</P>

<P>|幣別|所有人|金</P>

<P>|無 I I </P>

<P>額 i折合新臺幣價額| </P>

<P>(七)有價證券(股票、票券、債券及其他有價證券總價額:994,790元) </P>

<P>1.股票(總價頻: 994,790 元)</P>

<P>一一</P>

<P>五一七七</P>

<Table>
<TR>
<TD>種類</TD>

<TD>所有人</TD>

<TD>股</TD>

<TD>數</TD>

<TD>票面價額</TD>

<TD>總</TD>

<TD>額</TD>
</TR>

<TR>
<TD>太電</TD>

<TD>蘇淑瞳 </TD>

<TD/>

<TD>12,573 </TD>

<TD>10 </TD>

<TD/>

<TD>125,730 </TD>
</TR>

<TR>
<TD>永大</TD>

<TD>蘇淑嗤 </TD>

<TD/>

<TD>12,374 </TD>

<TD>10 </TD>

<TD/>

<TD>123,740 </TD>
</TR>

<TR>
<TD>一銀</TD>

<TD>蘇淑嗤 </TD>

<TD/>

<TD>2,933 </TD>

<TD>10 </TD>

<TD/>

<TD>29,330 </TD>
</TR>

<TR>
<TD>開發</TD>

<TD>蘇淑瞳 </TD>

<TD/>

<TD>13,325 </TD>

<TD>10 </TD>

<TD/>

<TD>133,250 50,130</TD>
</TR>

<TR>
<TD>榮電</TD>

<TD>蘇淑瞳 </TD>

<TD/>

<TD>5,013 </TD>

<TD>10 '-</TD>
</TR>
</Table>

<Table>
<TR>
<TH>國票</TH>

<TH>蘇激瞳 </TH>

<TH>2, 071 </TH>

<TH>10 </TH>

<TH>20, 710 </TH>
</TR>

<TR>
<TH>華新</TH>

<TH>蘇淑嗤 </TH>

<TD>804 </TD>

<TD>10 </TD>

<TD>8, 040 </TD>
</TR>

<TR>
<TH>三商行</TH>

<TH>蘇淑瞳 </TH>

<TD>6, 000 </TD>

<TD>10 </TD>

<TD>60 , 000 </TD>
</TR>

<TR>
<TH>圖書</TH>

<TH>蘇淑瞳 </TH>

<TD>2, 000 </TD>

<TD>10 </TD>

<TD>20, 000 </TD>
</TR>

<TR>
<TH>世華銀行(未上市)</TH>

<TH>蘇淑瞳 </TH>

<TD>36, 300 </TD>

<TD>10 </TD>

<TD>363, 000 </TD>
</TR>

<TR>
<TH>台灣中小企銀(未上市)L </TH>

<TH>許新校 </TH>

<TD>6, 086 </TD>

<TD>10 </TD>

<TD>60, 860 </TD>
</TR>
</Table>

<P>2.票券(總價額:</P>

<P>所所類教 </P>

<P>有</P>
</Sect>
</Part>

<Part>
<H1>人巨型</H1>

<P>有</P>

<P>人哲票面價額|總</P>

<L>
<LI>
<Lbl>3.</Lbl>

<LBody>債券(總價頻: </LBody>
</LI>

<LI>
<Lbl>4.</Lbl>

<LBody>其他有價證券(總價頻:</LBody>
</LI>
</L>

<P>類</P>

<P>時1 </P>

<P>.',, </P>

<P>有</P>

<P>人曾 票面價頒|總</P>

<P>產種類</P>

<P>所</P>

<P>有價</P>

<P>人</P>

<P>財 </P>

<P>額</P>

<P>台北高爾夫俱樂部會員証許新校1, 600, 000 </P>

<P>(九)債權(總金頻:元)</P>

<P>|種類|債權</P>

<P>人</P>

<P>債</P>

<P>務人及地</P>

<P>金</P>

<P>址</P>

<P>|無|</P>

<P>(十)債務(總金額:元)</P>

<P>|種類|債</P>

<P>務</P>

<P>人</P>

<P>債</P>

<P>權</P>

<P>金</P>

<P>址</P>

<P>人及地</P>

<P>|無|</P>

<P>∞事業投資(總金額:8, 100,000 元)</P>

<Table>
<TR>
<TD>投資人</TD>

<TD>投實事業名</TD>

<TD>稱</TD>

<TD>及</TD>

<TD>地</TD>

<TD>起k</TD>

<TD>投資金額</TD>
</TR>

<TR>
<TD>蘇淑瞳</TD>

<TD>草口北書建市南設股京份東有路3限段公33司8巷3號7樓 </TD>

<TD/>

<TD/>

<TD/>

<TD/>

<TD>3， 000， 00。</TD>
</TR>

<TR>
<TD>蘇淑瞳</TD>

<TD>泰桃安園証市券中股正路份有133限號公5樓司 . </TD>

<TD/>

<TD/>

<TD/>

<TD/>

<TD>5, 100, 000 </TD>
</TR>
</Table>

<P>監察院公報公職人員財產申報資料專刊</P>

<P>第十九期</P>

<P>五一七八</P>
</Part>

<Part>
<H1>陣巨
</H1>

<P>監察院公報</P>

<P>此致監察院</P>

<P>(受理申報機關〔構〕全稱)</P>

<P>公職人員財產申報資料專刊</P>

<P>以上資料，本人係依法誠實申報，如有不賞，顧負法律責任。申報人:許新校申報日期: 83年 12月 30日</P>

<Sect>
<H2>空</H2>

<P>九期五一七九</P>
</Sect>
</Part>
</TaggedPDF-doc>
