<?xml version="1.0" encoding="UTF-8" ?>
<!-- Created from PDF via Acrobat SaveAsXML -->
<!-- Mapping Table version: 28-February-2003 -->
<TaggedPDF-doc>
<?xpacket begin='﻿' id='W5M0MpCehiHzreSzNTczkc9d'?>
<?xpacket begin="﻿" id="W5M0MpCehiHzreSzNTczkc9d"?>
<x:xmpmeta xmlns:x="adobe:ns:meta/" x:xmptk="Adobe XMP Core 5.4-c005 78.147326, 2012/08/23-13:03:03        ">
   <rdf:RDF xmlns:rdf="http://www.w3.org/1999/02/22-rdf-syntax-ns#">
      <rdf:Description rdf:about=""
            xmlns:xmp="http://ns.adobe.com/xap/1.0/"
            xmlns:xmpMM="http://ns.adobe.com/xap/1.0/mm/"
            xmlns:dc="http://purl.org/dc/elements/1.1/"
            xmlns:pdf="http://ns.adobe.com/pdf/1.3/">
         <xmp:ModifyDate>2007-10-25T16:21:30+08:00</xmp:ModifyDate>
         <xmp:CreateDate>2007-10-25T16:21:19+08:00</xmp:CreateDate>
         <xmp:MetadataDate>2007-10-25T16:21:30+08:00</xmp:MetadataDate>
         <xmpMM:DocumentID>uuid:d66f193a-3455-4f23-a272-32868c5fabe3</xmpMM:DocumentID>
         <xmpMM:InstanceID>uuid:b99bd67d-0adc-4a03-8e6e-055918ed909c</xmpMM:InstanceID>
         <dc:format>xml</dc:format>
         <pdf:Producer>Adobe Acrobat Pro 11.0.0 Paper Capture Plug-in</pdf:Producer>
      </rdf:Description>
   </rdf:RDF>
</x:xmpmeta>
                                                                                                    
                                                                                                    
                                                                                                    
                                                                                                    
                                                                                                    
                                                                                                    
                                                                                                    
                                                                                                    
                                                                                                    
                                                                                                    
                                                                                                    
                                                                                                    
                                                                                                    
                                                                                                    
                                                                                                    
                                                                                                    
                                                                                                    
                                                                                                    
                                                                                                    
                                                                                                    
                           
<?xpacket end="w"?>
<?xpacket end='r'?>

<P>/;\、 員產申</P>

<P>A 職人財報表</P>

<P>監察院公報公職人員財產申報資料專刊第二一期五六三五</P>

<Table>
<TR>
<TH>申報人姓名</TH>

<TH>葉正林</TH>

<TH>服務機關</TH>

<TH>1.國民大會</TH>

<TH/>

<TH>職稱 </TH>

<TH>1.國大代表</TH>
</TR>

<TR>
<TD>2. </TD>

<TD/>

<TD>2. </TD>
</TR>

<TR>
<TH>配偶</TH>

<TD>及未成年子</TD>

<TD>女</TD>

<TD>配偽及</TD>

<TD>未成年子女|</TD>
</TR>

<TR>
<TH>稱</TH>

<TD>謂</TD>

<TD>姓</TD>

<TD>名</TD>

<TD>稱</TD>

<TD>謂</TD>

<TD>姓名</TD>
</TR>

<TR>
<TH>妻</TH>

<TD/>

<TD>葉魏玉鳳</TD>

<TD/>

<TD>重女</TD>

<TD/>

<TD>葉JL'如</TD>
</TR>
</Table>

<P>(一)不動產</P>

<L>
<LI>
<Lbl>1.</Lbl>

<LBody>土地</LBody>
</LI>

<LI>
<Lbl>2.</Lbl>

<LBody>房屋</LBody>
</LI>
</L>

<Table>
<TR>
<TH>土地坐落</TH>

<TH>面積(平方公尺)</TH>

<TH>權利範圍〈持分)</TH>

<TH>所有權人</TH>
</TR>

<TR>
<TH>中壢市埔頂段 1234地號 </TH>

<TD>346 </TD>

<TD>10000分之2445</TD>

<TD>葉正林</TD>
</TR>

<TR>
<TH>中壢市興南小段209-31地號(興南段) </TH>

<TD>2, 068 </TD>

<TD>100000分之8029</TD>

<TD>葉正林</TD>
</TR>

<TR>
<TH>中壢市平寮段 1324地號 </TH>

<TD>433 </TD>

<TD>2分之l</TD>

<TD>葉正林</TD>
</TR>

<TR>
<TH>中壢市平寮段 1324-1地號 </TH>

<TD>97 </TD>

<TD>2分之l</TD>

<TD>葉正林</TD>
</TR>

<TR>
<TH>中壢市平寮段 1324-2地號 </TH>

<TD>40 </TD>

<TD>2分之l</TD>

<TD>葉正林</TD>
</TR>

<TR>
<TH>中壢市種興段 1989地號 </TH>

<TD>196 </TD>

<TD>10分之l</TD>

<TD>葉魏玉鳳</TD>
</TR>

<TR>
<TH>中壢市價興段 1987地號 </TH>

<TD>194 </TD>

<TD>10分之l</TD>

<TD>葉正林</TD>
</TR>

<TR>
<TH>中壢市復興段 1532地號 </TH>

<TD>135 </TD>

<TD>所有權全部</TD>

<TD>葉正林</TD>
</TR>

<TR>
<TH>中壢市復興段 1537地號 </TH>

<TD>900 </TD>

<TD>所有權全部</TD>

<TD>葉正林</TD>
</TR>

<TR>
<TH>中壢市中工段 1637地號 </TH>

<TD>506 </TD>

<TD>10000分之977</TD>

<TD>葉正林</TD>
</TR>

<TR>
<TH>中壢市中工段681地號 </TH>

<TD>88 </TD>

<TD>所有權全部</TD>

<TD>葉正林</TD>
</TR>

<TR>
<TH>中壢市復興段 1436地號 </TH>

<TD>177 </TD>

<TD>185分之7</TD>

<TD>葉正林</TD>
</TR>

<TR>
<TH>中壢市復興段 1419地號 </TH>

<TD>1, 184 </TD>

<TD>1215分之 1175</TD>

<TD>葉正林</TD>
</TR>

<TR>
<TH>中壢市復興段 1433地號 </TH>

<TD>233 </TD>

<TD>224分之135</TD>

<TD>葉正林</TD>
</TR>

<TR>
<TH>中壢市復興段 1550地號 </TH>

<TD>591 </TD>

<TD>所有權全部</TD>

<TD>葉正林</TD>
</TR>

<TR>
<TH>中壢市復興段 1434地號 </TH>

<TD>800 </TD>

<TD>8113分之526</TD>

<TD>葉正林</TD>
</TR>

<TR>
<TH>中壢市復興段 1576地號 </TH>

<TD>395 </TD>

<TD>所有權全部</TD>

<TD>葉正林</TD>
</TR>

<TR>
<TH>中壢市環東段941地號 </TH>

<TD>115 </TD>

<TD>4分之l</TD>

<TD>葉正林</TD>
</TR>

<TR>
<TH>中壢市環東段896地號 </TH>

<TD>110 </TD>

<TD>4分之1</TD>

<TD>葉正林</TD>
</TR>

<TR>
<TH>中壢市環東段903地號 </TH>

<TD>38 </TD>

<TD>4分之l</TD>

<TD>葉正林</TD>
</TR>

<TR>
<TH>八德鄉大華3地段號的， 100, 10 1, 102, 104, 102-1,102-2, 10 </TH>

<TD>2, 227 </TD>

<TD>120分之45</TD>

<TD>葉正林 </TD>
</TR>
</Table>

<Table>
<TR>
<TD>平鎮市服連墟段122-15地號 </TD>

<TD>29 </TD>

<TD>所有權全部</TD>

<TD>葉正林</TD>
</TR>

<TR>
<TD>平鎮市取連坡段125-30地號 </TD>

<TD>124 </TD>

<TD>所有權全部</TD>

<TD>葉正林</TD>
</TR>

<TR>
<TD>平鎮市平鎮段1173地號 </TD>

<TD>2, 307.73 </TD>

<TD>10000分之280</TD>

<TD>葉正林</TD>
</TR>

<TR>
<TD>平鎮市平鎮段1005地號 </TD>

<TD>5, 807 </TD>

<TD>10000分之384</TD>

<TD>葉正林</TD>
</TR>

<TR>
<TD>平鎮市平鎮段1157地號 </TD>

<TD>614.90 </TD>

<TD>所有權全部</TD>

<TD>葉正林</TD>
</TR>

<TR>
<TD>平鎮市平鎮段Il48地號 </TD>

<TD>561.01 </TD>

<TD>所有權全部</TD>

<TD>葉正林</TD>
</TR>

<TR>
<TD>平鎮市平鎮段Il61地號 </TD>

<TD>284. 22 </TD>

<TD>所有權全部</TD>

<TD>葉正林</TD>
</TR>

<TR>
<TD>平鎮市平鎮段1181地號 </TD>

<TD>297.40 </TD>

<TD>所有權全部</TD>

<TD>葉正林</TD>
</TR>

<TR>
<TD>平鎮市平鎮段Il84地號 </TD>

<TD>404.34 </TD>

<TD>所有權全部</TD>

<TD>葉正林 </TD>
</TR>
</Table>

<Table>
<TR>
<TD>房屋標 πT </TD>

<TD>面積(平方公尺)</TD>

<TD>權利範園(持分)</TD>

<TD>所有權人</TD>
</TR>

<TR>
<TD>中壢市埔頂段1234地號及建號12556 </TD>

<TD>39.22 </TD>

<TD>所有權全部</TD>

<TD>葉正林</TD>
</TR>

<TR>
<TD>中壢市埔頂段1234地號及建號12521 </TD>

<TD>102.93 </TD>

<TD>所有權全部</TD>

<TD>葉正林</TD>
</TR>

<TR>
<TD>中壢市埔頂段1234地號及建號12519 </TD>

<TD>102.93 </TD>

<TD>所有權全部</TD>

<TD>葉正林</TD>
</TR>

<TR>
<TD>中壢市埔頂段1234地號及建號12523 </TD>

<TD>103.08 </TD>

<TD>所有權全部</TD>

<TD>葉正林</TD>
</TR>

<TR>
<TD>中壢市埔頂段1234地號及建號12517 </TD>

<TD>43. 98 </TD>

<TD>2分之l</TD>

<TD>葉正林</TD>
</TR>

<TR>
<TD>中壢市興南段興南小段209-31地號及建號 3915 </TD>

<TD>157.94 </TD>

<TD>所有權全部</TD>

<TD>葉正林 </TD>
</TR>

<TR>
<TD>中壢市興南段興南小段209-31地號及建號 3916 </TD>

<TD>128.74 </TD>

<TD>所有權全部</TD>

<TD>葉正林 </TD>
</TR>

<TR>
<TD>中壢市興南段興南小段209-31地號及建號 4003 </TD>

<TD>1, 606.42 </TD>

<TD>100000分之6130</TD>

<TD>葉正林 </TD>
</TR>

<TR>
<TD>中壢市興南段興南小段209-31地號及建號 4002 </TD>

<TD>1, 040.43 </TD>

<TD>100000分之8332</TD>

<TD>葉正林 </TD>
</TR>

<TR>
<TD>中壢市興南段興南小段209-31地號及建號 3912 </TD>

<TD>124.07 </TD>

<TD>所有權全部</TD>

<TD>葉正林 </TD>
</TR>

<TR>
<TD>中壢市興南段興南小段209-31地號及建號 3913 </TD>

<TD>110. 21 </TD>

<TD>所有權全部</TD>

<TD>葉正林 </TD>
</TR>

<TR>
<TD>中壢市興南段興南小段209-31地號及建號 3914 </TD>

<TD>150.78 </TD>

<TD>所有權全部</TD>

<TD>葉正林 </TD>
</TR>

<TR>
<TD>中壢市興南段興南小段209-31地號及建號 3917 </TD>

<TD>207.65 </TD>

<TD>所有權全部 </TD>

<TD/>
</TR>

<TR>
<TD>中壢市平寮段1324.1324寸， 1324-2地號及建號 905 </TD>

<TD>77 </TD>

<TD>2分之l</TD>

<TD>葉正林 </TD>
</TR>
</Table>

<P>監察院公報公職人員財產申報資料專刊第二一期五六三六</P>

<P>監察院公報公職人員財產申報資料專刊第二一期五六三七 </P>

<Table>
<TR>
<TH>中壢市復興段 1989地號及建號 1868 中壢市復興段 1987地號及建號 1833 中壢市復興段 1532地號及建號 1685 中壢市復興段 1536， 1537地號及建號792 中壢市復興段 1536， 1537地號及建號793 中壢市中工段 1637地號及建號2760 中壢市中工段 1637地號及建號2763 平鎮市平鎮段 1005地號及建號3036 平鎮市平鎮段 1005地號及建號3049 平鎮市平鎮段 1005地號及建號3051 平鎮市平鎮段 1173地號及建號3103 </TH>

<TH>87.16 87.16 176.20 25 1. 60 269.36 61. 96 267.06 152 152 152 133 </TH>

<TH>所有權全部所有權全部所有權全部所有權全部所有權全部所有權全部18分之II所有權全部所有權全部所有權全部所有權全部</TH>

<TH>葉魏玉鳳葉正林葉正林葉正林葉正林葉正林葉正林葉正林葉正林葉正林葉正林</TH>
</TR>
</Table>

<Part>
<H1>司」
</H1>

<P>船數</P>

<P>籍</P>

<P>所港</P>

<P>有</P>

<P>噸</P>
</Part>

<Part>
<H1>于
</H1>

<Sect>
<H4>製進廠名稱|國籍標示及編號|所有</H4>

<P>1 </P>

<P>(五)存款(總金頻:4, 320, 000 元)</P>

<P>1.新臺幣存款</P>
</Sect>

<Sect>
<H3>|無</H3>

<Table>
<TR>
<TH>種</TH>

<TH>類 </TH>

<TH>A. </TH>

<TH>缸令.b </TH>

<TH>量</TH>

<TH>牌 AA、</TH>

<TH>號</TH>

<TH>碼</TH>

<TH>所</TH>

<TH>有</TH>

<TH>人</TH>
</TR>

<TR>
<TH>小客車 小客車 </TH>

<TD/>

<TD/>

<TD>3, 000cc </TD>

<TD/>

<TD>KP-9988 </TD>

<TD/>

<TD/>

<TD>葉正林</TD>

<TD/>

<TD/>
</TR>

<TR>
<TD/>

<TD>3, OOOcc </TD>

<TD/>

<TD>KM-9788 </TD>

<TD/>

<TD/>

<TD>魏玉鳳</TD>

<TD/>

<TD/>
</TR>
</Table>

<P>(四)航空器 </P>
<Figure>

<ImageData src=""/>
種類存放機構戶名金活期存款中壢土地銀行葉正林3, 240, 000 支票存款內壢台企銀行葉正林1, 080, 000 一----------</Figure>

<P>2.外幣反其他幣別存款</P>
<Figure>

<ImageData src=""/>
金頻幣&gt;N 存放機構戶名折合新臺幣價額種書長無ι-</Figure>

<P>監察院公報公職人員財產申報資料專刊</P>

<P>第二一期</P>

<P>五六三八</P>

<P>面貝</P>

<P>，</P>

<P>人</P>

<P>再</P>

<P>.',, </P>

<P>H1 </P>

<P>產種類有</P>

<P>教 </P>

<P>金</P>

<P>址</P>

<P>仇 </P>

<P>務人及地</P>

<P>HU </P>

<P>AHV nu nHUAHunU 元)</P>

<P>憤助</P>

<P>人</P>

<P>, .z' 有人哲</P>

<P>時1 </P>

<P>，作</P>

<P>1 </P>

<P>類類 </P>

<P>3.債券(總價額:元)</P>

<Table>
<TR>
<TH>(六)外幣(指現金或旅行支票)(總價額:</TH>

<TH>元)</TH>
</TR>

<TR>
<TH>|帶別|所有人|金</TH>

<TD>額|折合新臺幣價額|</TD>
</TR>

<TR>
<TH>|無 </TH>

<TD>I </TD>

<TD>I </TD>

<TD/>
</TR>

<TR>
<TH>(七)有價證券(股票、票券、積券及其他有價證券總價額:</TH>

<TD>元)</TD>
</TR>

<TR>
<TH>1.股票(總價額:</TH>

<TD>元)</TD>

<TD/>
</TR>

<TR>
<TH>類|所有人|股 </TH>

<TD/>
</TR>

<TR>
<TH>|| </TH>

<TD/>
</TR>

<TR>
<TH>2.票券(總領額:</TH>

<TD>元)</TD>

<TD/>
</TR>
</Table>

<P>Aι </P>

<P>有票面價額</P>
</Sect>

<Sect>
<H1>人哲</H1>

<P>有</P>

<P>人 E習</P>

<P>元)</P>

<P>..</P>

<P>', </P>

<Table>
<TR>
<TD>種報抵押貸款</TD>

<TD>債務人葉正林</TD>

<TD>債權人新中竹壢企市銀龍東路78號 </TD>

<TD>及</TD>

<TD>地 </TD>

<TD>hl </TD>

<TD>金</TD>

<TD>額15, 000, 000 </TD>
</TR>

<TR>
<TD>抵押貸款</TD>

<TD>葉正林</TD>

<TD>新中竹壢企市銀中山東路二段27號 </TD>

<TD/>

<TD/>

<TD/>

<TD/>

<TD>5, 000, 000 I </TD>
</TR>

<TR>
<TD>抵押貸款</TD>

<TD>葉正林」</TD>

<TD>台中灣壢土市地中銀山行路190號 </TD>

<TD/>

<TD/>

<TD/>

<TD/>

<TD>45, 000, 000 I </TD>
</TR>
</Table>
</Sect>

<Sect>
<H1>區
</H1>

<P>4.其他有價證券(總價額:</P>

<P>權</P>

<P>tO事業投資(總金額:70, 000, 000 元)|投資人|投實 事業名稱及地起t資金</P>

<P>監察院公報公職人員財產申報資料專刊第二一期五六三九</P>

<Table>
<TR>
<TH>葉正林</TH>

<TH>通中壢省建市元設化(股路)公二段司45號12F </TH>

<TH>40, 000, 000 </TH>
</TR>

<TR>
<TD>葉魏玉鳳</TD>

<TD>過中壢省建市元設化(股路)公二段司45號12F </TD>

<TD>20, 000, 000 </TD>
</TR>

<TR>
<TD>葉正林</TD>

<TD>銀中泰壢建市元設化(股路)公165司巷35號12F </TD>

<TD>5, 000, 000 </TD>
</TR>

<TR>
<TD>葉魏玉鳳</TD>

<TD>銀中泰壢建市設元化(股路)公16司5巷35號12F </TD>

<TD>5， 000， 00。</TD>
</TR>
</Table>

<P>的備註</P>

<P>無</P>

<P>此致監察院</P>

<P>(受J理申報機關〔構〕全稱)以上資料，本人係依法誠實申報，如有不實，顧負法律責任。申報人:葉正林申報日期: 83年 12月 30日</P>
</Sect>
</Part>
</TaggedPDF-doc>
