<?xml version="1.0" encoding="UTF-8" ?>
<!-- Created from PDF via Acrobat SaveAsXML -->
<!-- Mapping Table version: 28-February-2003 -->
<TaggedPDF-doc>
<?xpacket begin='﻿' id='W5M0MpCehiHzreSzNTczkc9d'?>
<?xpacket begin="﻿" id="W5M0MpCehiHzreSzNTczkc9d"?>
<x:xmpmeta xmlns:x="adobe:ns:meta/" x:xmptk="Adobe XMP Core 5.4-c005 78.147326, 2012/08/23-13:03:03        ">
   <rdf:RDF xmlns:rdf="http://www.w3.org/1999/02/22-rdf-syntax-ns#">
      <rdf:Description rdf:about=""
            xmlns:xmp="http://ns.adobe.com/xap/1.0/"
            xmlns:dc="http://purl.org/dc/elements/1.1/"
            xmlns:xmpMM="http://ns.adobe.com/xap/1.0/mm/"
            xmlns:pdf="http://ns.adobe.com/pdf/1.3/">
         <xmp:ModifyDate>2007-11-05T16:45:40+08:00</xmp:ModifyDate>
         <xmp:CreateDate>2007-11-05T16:45:17+08:00</xmp:CreateDate>
         <xmp:MetadataDate>2007-11-05T16:45:40+08:00</xmp:MetadataDate>
         <xmp:CreatorTool>Adobe Acrobat 7.08</xmp:CreatorTool>
         <dc:format>xml</dc:format>
         <xmpMM:DocumentID>uuid:f50a1f8b-04d3-4d1f-995a-e4a181fa716f</xmpMM:DocumentID>
         <xmpMM:InstanceID>uuid:bf715e78-1068-48ac-805d-065dd6618c83</xmpMM:InstanceID>
         <pdf:Producer>Adobe Acrobat Pro 11.0.0 Paper Capture Plug-in</pdf:Producer>
      </rdf:Description>
   </rdf:RDF>
</x:xmpmeta>
                                                                                                    
                                                                                                    
                                                                                                    
                                                                                                    
                                                                                                    
                                                                                                    
                                                                                                    
                                                                                                    
                                                                                                    
                                                                                                    
                                                                                                    
                                                                                                    
                                                                                                    
                                                                                                    
                                                                                                    
                                                                                                    
                                                                                                    
                                                                                                    
                                                                                                    
                                                                                                    
                           
<?xpacket end="w"?>
<?xpacket end='r'?>

<P>r.、.</P>

<P>品3、</P>

<P>職 </P>

<P>員財產申報表</P>

<Part>
<H2>人</H2>

<P>土地坐落</P>

<P>權利範園(持分)</P>

<Sect>
<H3>所有權人 l</H3>

<P>(面平方公尺積) </P>

<P>程惠卿</P>

<P>基隆市安樂區大竿林段的地號 </P>

<P>1000分之99</P>

<P>1,050 </P>

<P>程惠卿</P>

<P>基陸市安樂區大竿林段80-1地號 </P>

<P>739 </P>

<P>120分之l</P>

<P>程惠卿</P>

<P>基陸市安樂區大竿林段80-13地號 </P>

<P>760 </P>

<P>120分之l</P>

<P>程惠卿</P>

<P>基隆市安樂區大竿林段駒-16地號 </P>

<P>221 </P>

<P>120分之l</P>

<P>程惠卿</P>

<P>基隆市安樂區大竿林段80-17地號 </P>

<P>925 </P>

<P>120分之l</P>

<P>程惠卿</P>

<P>基陸市安樂區大竿林段80-25地號 </P>

<P>236 </P>

<P>120分之l</P>

<P>程惠卿</P>

<P>基隆市安樂區大竿林段80-訝地號 </P>

<P>347 </P>

<P>120分之l</P>

<P>程惠卿</P>

<P>基隆市安樂區大竿林段80-29地號 </P>

<P>472 </P>

<P>120分之l</P>

<P>程惠卿</P>

<P>基陸市安樂區大竿林段80-33地號 </P>

<P>598 </P>

<P>120分之l</P>

<Table>
<TR>
<TH/>

<TH/>

<TH/>

<TH/>

<TH/>

<TH/>

<TH/>

<TH/>
</TR>

<TR>
<TD/>

<TD/>

<TD/>

<TD>l.台灣省議會</TD>

<TD/>

<TD/>

<TD>l.議員</TD>

<TD/>
</TR>

<TR>
<TD>申報人姓名</TD>

<TD>程惠卿</TD>

<TD>服務機關</TD>

<TD/>

<TD/>

<TD>職稱 </TD>

<TD/>

<TD/>
</TR>

<TR>
<TD/>

<TD/>

<TD/>

<TD>2. </TD>

<TD/>

<TD/>

<TD>2. </TD>

<TD/>
</TR>

<TR>
<TD>商己偶</TD>

<TD>及未成年子</TD>

<TD>女</TD>

<TD>商已偶及</TD>

<TD>未成年子</TD>

<TD>女</TD>
</TR>

<TR>
<TD>稱</TD>

<TD>謂</TD>

<TD>姓</TD>

<TD>名</TD>

<TD>稱</TD>

<TD>謂</TD>

<TD>姓</TD>

<TD>名</TD>
</TR>

<TR>
<TD>長子</TD>

<TD/>

<TD>陳駿豪</TD>

<TD/>

<TD>次于</TD>

<TD/>

<TD>陳駿霆</TD>

<TD/>
</TR>
</Table>

<P>(一)不動產</P>

<L>
<LI>
<Lbl>1.</Lbl>

<LBody>土地</LBody>
</LI>

<LI>
<Lbl>2.</Lbl>

<LBody>房屋</LBody>
</LI>
</L>

<Table>
<TR>
<TD>房屋標可T</TD>

<TD>面(平方公尺積) </TD>

<TD>權利範園(持分)</TD>

<TD>所有權人</TD>
</TR>

<TR>
<TD>基164隆市外木山段124-114小段124-366小段建號 </TD>

<TD>142.78 </TD>

<TD>所有權全部</TD>

<TD>程惠卿</TD>
</TR>

<TR>
<TD>基隆市安樂區大竿林段80地號建號252 </TD>

<TD>165.65 </TD>

<TD>所有權全部</TD>

<TD>程惠卿</TD>
</TR>
</Table>

<P>，</P>

<Sect>
<H3>但一種一無一倍</H3>

<P>一三二六</P>

<P>種</P>

<P>總類</P>

<P>辦一車船一汽</P>

<P>、自'，-、 </P>

<P>噸</P>

<P>籍</P>

<P>港</P>

<P>再</P>

<P>.缸，</P>

<P>H1</P>

<P>有</P>

<P>1'</P>

<P>紅是﹒</P>

<P>類汽缸告量牌~{\ 號 司馬所有</P>

<P>監察院公報公職人員財產申報資料專刊第四七期 </P>

<Sect>
<H3>人</H3>

<P>小客車1,295cc 1K7190 程惠卿 </P>

<P>(四)航空器</P>

<P>|型式|製造廠名稱|國籍標示及編號|所有</P>
</Sect>
</Sect>
</Sect>

<Sect>
<H3>|無|</H3>

<P>(五)存款(總金額:</P>

<P>l.新臺幣存款835 ,174 元)</P>

<Table>
<TR>
<TH>種</TH>

<TH>類</TH>

<TH>存放機</TH>

<TH>構</TH>

<TH>戶</TH>

<TH>名</TH>

<TH>金</TH>

<TH>額</TH>
</TR>

<TR>
<TD>活儲</TD>

<TD/>

<TD>中國國際商銀</TD>

<TD/>

<TD>程惠卿 </TD>

<TD/>

<TD/>

<TD>177 ， 5的</TD>
</TR>

<TR>
<TD>活儲</TD>

<TD/>

<TD>基隆市第刊盲用合作社</TD>

<TD/>

<TD>程惠卿 </TD>

<TD/>

<TD/>

<TD>657 ,630 </TD>
</TR>
</Table>

<P>2.外幣及其他幣別存款</P>

<P>監察院公報人</P>

<P>公職人員財產申報資料專刊第四七期一一二二↓八 </P>

<Table>
<TR>
<TD>種機放存別幣類 L (六)外幣(指現金或旅行支票)(總價額:|幣別 l所有人|金|無 I I (七)有價證券(股票、票券、債券及其他有價證券總價額:一一l.股票(總價額:元)無</TD>

<TD>斗寸刮</TD>

<TD>名|金額||折合新臺幣價額| L一_j 額|折合新臺幣價額|元)</TD>
</TR>

<TR>
<TD>類|所有人|股 || </TD>

<TD>票面價額 </TD>
</TR>

<TR>
<TD>2.票券(總價額:</TD>

<TD/>
</TR>
</Table>
</Sect>
</Part>

<Part>
<H1>刊土</H1>

<P>有</P>

<Sect>
<H1>生 人 I~~.I</H1>

<P>3.債券(總價額:</P>

<P>有</P>

<Sect>
<H1>人會</H1>

<P>4.其他有價證券(總價額:</P>
</Sect>
</Sect>
</Part>

<Part>
<H1>吋土
</H1>

<Sect>
<P>有</P>
</Sect>

<Sect>
<Sect>
<H1>人曾</H1>

<P>產種類有</P>

<P>產一財一他一其一</P>
</Sect>

<P>恃 KI同匡</P>

<P>國貝</P>

<P>人</P>

<P>(九)債權(總金額:元)</P>

<P>|種類|債</P>

<Sect>
<P>權</P>

<P>人</P>

<P>債</P>

<P>務人及</P>

<P>金</P>

<P>地</P>

<P>址</P>
</Sect>

<Sect>
<H3>|無|</H3>

<P>(十)債務(總金額:元)</P>

<P>|種類|債</P>

<Sect>
<P>務</P>

<P>人</P>

<P>債</P>

<P>金</P>

<P>址</P>

<P>權及地</P>

<P>人</P>
</Sect>

<Table>
<TR>
<TH>|無| </TH>
</TR>

<TR>
<TH>t母事業投資(總金額:</TH>

<TD/>

<TD/>

<TD/>

<TD>元)</TD>
</TR>

<TR>
<TH>|投資人|</TH>

<TD>技</TD>

<TD>資</TD>

<TD>事</TD>

<TD>業</TD>

<TD>名</TD>

<TD>稱</TD>

<TD>及</TD>

<TD>地</TD>

<TD>址</TD>

<TD>資</TD>

<TD>金</TD>
</TR>

<TR>
<TH>|無|</TH>

<TD/>

<TD/>

<TD/>

<TD/>

<TD/>

<TD/>

<TD/>

<TD/>

<TD/>

<TD/>
</TR>

<TR>
<TH>的備註</TH>

<TD/>

<TD/>

<TD/>

<TD/>

<TD/>

<TD/>

<TD/>

<TD/>

<TD/>

<TD/>
</TR>
</Table>

<P>無</P>

<Sect>
<P>此致監察院</P>

<P>(受理申報機關〔構〕全稱)</P>
</Sect>

<P>以上資料，本人係依法誠實申報，如有不實，願負法律責任。</P>

<P>報人:程惠卿申報日期: 85年 12月 30日</P>

<Sect>
<P>監察院公報公職人員財產申報資料專刊第四七期</P>

<P>申</P>
</Sect>

<P>一三二六(</P>
</Sect>
</Sect>
</Part>
</TaggedPDF-doc>
