<?xml version="1.0" encoding="UTF-8" ?>
<!-- Created from PDF via Acrobat SaveAsXML -->
<!-- Mapping Table version: 28-February-2003 -->
<TaggedPDF-doc>
<?xpacket begin='﻿' id='W5M0MpCehiHzreSzNTczkc9d'?>
<?xpacket begin="﻿" id="W5M0MpCehiHzreSzNTczkc9d"?>
<x:xmpmeta xmlns:x="adobe:ns:meta/" x:xmptk="Adobe XMP Core 5.4-c005 78.147326, 2012/08/23-13:03:03        ">
   <rdf:RDF xmlns:rdf="http://www.w3.org/1999/02/22-rdf-syntax-ns#">
      <rdf:Description rdf:about=""
            xmlns:xmp="http://ns.adobe.com/xap/1.0/"
            xmlns:dc="http://purl.org/dc/elements/1.1/"
            xmlns:xmpMM="http://ns.adobe.com/xap/1.0/mm/"
            xmlns:pdf="http://ns.adobe.com/pdf/1.3/">
         <xmp:ModifyDate>2007-11-05T16:49:25+08:00</xmp:ModifyDate>
         <xmp:CreateDate>2007-11-05T16:49:20+08:00</xmp:CreateDate>
         <xmp:MetadataDate>2007-11-05T16:49:25+08:00</xmp:MetadataDate>
         <xmp:CreatorTool>Adobe Acrobat 7.08</xmp:CreatorTool>
         <dc:format>xml</dc:format>
         <xmpMM:DocumentID>uuid:1c9bc961-0488-46e8-9942-c93bcc47f3df</xmpMM:DocumentID>
         <xmpMM:InstanceID>uuid:73a243e1-17d6-4ecf-a7e9-c8def0411355</xmpMM:InstanceID>
         <pdf:Producer>Adobe Acrobat Pro 11.0.0 Paper Capture Plug-in</pdf:Producer>
      </rdf:Description>
   </rdf:RDF>
</x:xmpmeta>
                                                                                                    
                                                                                                    
                                                                                                    
                                                                                                    
                                                                                                    
                                                                                                    
                                                                                                    
                                                                                                    
                                                                                                    
                                                                                                    
                                                                                                    
                                                                                                    
                                                                                                    
                                                                                                    
                                                                                                    
                                                                                                    
                                                                                                    
                                                                                                    
                                                                                                    
                                                                                                    
                           
<?xpacket end="w"?>
<?xpacket end='r'?>

<P>公</P>

<P>職</P>

<P>員財產</P>

<P>人</P>

<P>申</P>

<P>報</P>

<P>表</P>

<P>監察院公報公職人員財產申報資料專刊第四八期</P>

<Table>
<TR>
<TH>申報人姓名</TH>

<TH>陳超明</TH>

<TH>服務機關</TH>

<TH>l.台灣省議會</TH>

<TH/>

<TH>職稱 </TH>

<TH>l.議員2.</TH>

<TH/>
</TR>

<TR>
<TD>2. </TD>

<TD/>
</TR>

<TR>
<TH>自己偶</TH>

<TD>及未成年子</TD>

<TD>女</TD>

<TD>商己偶及</TD>

<TD>未成</TD>

<TD>年子</TD>

<TD>女</TD>
</TR>

<TR>
<TH>幸存</TH>

<TD>謂</TD>

<TD>姓 </TD>

<TD>J巴</TD>

<TD>幸存</TD>

<TD>謂</TD>

<TD>姓</TD>

<TD/>

<TD>名</TD>
</TR>

<TR>
<TH>妻子</TH>

<TD/>

<TD>吳麗利</TD>

<TD/>

<TD>長子</TD>

<TD/>

<TD>陳一豪</TD>

<TD/>

<TD/>
</TR>

<TR>
<TH>次子</TH>

<TD/>

<TD>陳志豪</TD>

<TD/>

<TD/>

<TD/>

<TD/>

<TD/>

<TD/>
</TR>
</Table>

<P>(一)不動產</P>

<P>1.土地</P>

<Table>
<TR>
<TH>土地坐落</TH>

<TH>(面平方公尺積) </TH>

<TH>權利範園(持分)</TH>

<TH>所有權人</TH>
</TR>

<TR>
<TH>苗栗縣頭份鎮濫坑段273地號 </TH>

<TD>1,276 </TD>

<TD>3分之l</TD>

<TD>陳超明</TD>
</TR>

<TR>
<TH>苗栗縣頭份鎮濫坑段273-14地號 </TH>

<TD>125 </TD>

<TD>3分之l</TD>

<TD>陳超明</TD>
</TR>

<TR>
<TH>苗栗縣頭份鎮濫坑段273-15地號 </TH>

<TD>331 </TD>

<TD>3分之l</TD>

<TD>陳超明</TD>
</TR>

<TR>
<TH>苗栗縣頭份鎮濫坑段273-16地號 </TH>

<TD>2,008 </TD>

<TD>3分之l</TD>

<TD>陳超明</TD>
</TR>

<TR>
<TH>苗栗縣頭份鎮濫坑段273-17地號 </TH>

<TD>731 </TD>

<TD>3分之l</TD>

<TD>陳超明</TD>
</TR>

<TR>
<TH>苗栗縣頭份鎮濫坑段273-18地號</TH>

<TD>10吐 </TD>

<TD>3分之1</TD>

<TD>陳超明</TD>
</TR>

<TR>
<TH>苗栗縣頭份鎮濫坑段273-19地號 </TH>

<TD>140 </TD>

<TD>3分之I</TD>

<TD>陳超明</TD>
</TR>

<TR>
<TH>苗栗縣頭份鎮濫坑段273-20地號 </TH>

<TD>73 </TD>

<TD>3分之l</TD>

<TD>陳超明</TD>
</TR>

<TR>
<TH>苗栗縣頭份鎮濫坑段273-21地號 </TH>

<TD>12 </TD>

<TD>3分之l</TD>

<TD>陳超明</TD>
</TR>

<TR>
<TH>苗栗縣頭份鎮濫坑段273-22地號 </TH>

<TD>50 </TD>

<TD>3分之l</TD>

<TD>陳超明</TD>
</TR>

<TR>
<TH>苗栗縣竹南鎮海口段海口小段380-2地號 </TH>

<TD>1,735 </TD>

<TD>3分之 I</TD>

<TD>陳超明</TD>
</TR>

<TR>
<TH>苗栗縣竹南鎮大埔段中大埔小段277-3地號 </TH>

<TD>93 </TD>

<TD>180965分之3883</TD>

<TD>陳超明</TD>
</TR>

<TR>
<TH>苗栗縣竹南鎮大埔段中大埔小段308-6地號 </TH>

<TD>136 </TD>

<TD>3600分之33</TD>

<TD>陳超明</TD>
</TR>

<TR>
<TH>苗栗縣竹南鎮大埔段中大埔小段308-23地號 </TH>

<TD>71 </TD>

<TD>3600分之33</TD>

<TD>陳超明</TD>
</TR>

<TR>
<TH>苗栗縣竹南鎮竹南段2小段836地號 </TH>

<TD>96 </TD>

<TD>5分之l</TD>

<TD>陳超明</TD>
</TR>

<TR>
<TH>苗栗縣竹南鎮中興段820地號 </TH>

<TD>3,591 </TD>

<TD>25分之2</TD>

<TD>陳超明</TD>
</TR>

<TR>
<TH>苗栗縣竹南鎮中興段828-5地號 </TH>

<TD>325 </TD>

<TD>25分之2</TD>

<TD>陳超明</TD>
</TR>

<TR>
<TH>苗栗縣竹南鎮中興段828-6地號 </TH>

<TD>188 </TD>

<TD>25分之2</TD>

<TD>陳超明</TD>
</TR>

<TR>
<TH>苗栗縣竹南鎮中興段博愛小段l地號 </TH>

<TD>1,149 </TD>

<TD>25分之2</TD>

<TD>陳超明</TD>
</TR>

<TR>
<TH>苗栗縣竹南鎮中興段博愛小段7地號 」一一一</TH>

<TD>1,269 </TD>

<TD>25分之2</TD>

<TD>陳超明</TD>
</TR>
</Table>

<P>一三五 九</P>

<P>O</P>

<Table>
<TR>
<TH>苗栗縣竹南鎮中興段博愛小段8地號 </TH>

<TH>628 </TH>

<TH>25分之2</TH>

<TH>陳超明</TH>
</TR>

<TR>
<TD>苗栗縣竹南鎮龍山段76地號 </TD>

<TD>94.27 </TD>

<TD>所有權全部</TD>

<TD>陳超明</TD>
</TR>

<TR>
<TD>苗栗縣竹南鎮龍山段 138地號 </TD>

<TD>5,877.20 </TD>

<TD>16792分之 153</TD>

<TD>陳超明</TD>
</TR>

<TR>
<TD>苗栗縣竹南鎮龍山段392地號 </TD>

<TD>341.69 </TD>

<TD>20分之I</TD>

<TD>陳超明</TD>
</TR>

<TR>
<TD>苗栗縣竹南鎮龍山段397地號 </TD>

<TD>182.10 </TD>

<TD>20分之l</TD>

<TD>陳超明</TD>
</TR>

<TR>
<TD>苗栗縣竹南鎮龍山段445地號 </TD>

<TD>323.95 </TD>

<TD>20分之l</TD>

<TD>陳超明</TD>
</TR>

<TR>
<TD>苗栗縣竹南鎮龍山段446地號 </TD>

<TD>83.30 </TD>

<TD>20分之l</TD>

<TD>陳超明</TD>
</TR>

<TR>
<TD>苗栗縣竹南鎮龍山段447地號 </TD>

<TD>202.79 </TD>

<TD>20分之l</TD>

<TD>陳超明</TD>
</TR>

<TR>
<TD>苗栗縣苗栗市嘉盛段513-8地號 </TD>

<TD>562.50 </TD>

<TD>所有權全部</TD>

<TD>陳超明</TD>
</TR>

<TR>
<TD>台北市敦化段3小段209地號 </TD>

<TD>452 </TD>

<TD>10000分之618</TD>

<TD>陳超明</TD>
</TR>

<TR>
<TD>台北市信義區福德段3小段243地號 </TD>

<TD>136 </TD>

<TD>4分之l</TD>

<TD>吳麗利</TD>
</TR>
</Table>

<P>2.房屋</P>

<Table>
<TR>
<TD>房屋標可t</TD>

<TD>面(平方公尺積) </TD>

<TD>權利範園(持分)</TD>

<TD>所有權人</TD>
</TR>

<TR>
<TD>台北市松山區敦化段3小段209地號建號1884 </TD>

<TD>l是 2.22</TD>

<TD>所有權全部</TD>

<TD>陳超明</TD>
</TR>

<TR>
<TD>苗用栗部縣份建竹南號鎮50龍5， 3山0段4) l38地號建號309(共同使 </TD>

<TD>139.97 </TD>

<TD>所有權全部</TD>

<TD>陳超明</TD>
</TR>

<TR>
<TD>台北市信義區福德段3小段243地號建號1386 </TD>

<TD>92.84 </TD>

<TD>所有權全部</TD>

<TD>吳麗利</TD>
</TR>

<TR>
<TD>苗用栗部份縣竹建南號鎮31龍7， 5山0段5) l38地號建號315(共同使 </TD>

<TD>148.18 </TD>

<TD>所有權全部</TD>

<TD>陳超明</TD>
</TR>
</Table>

<P>監察院公報公職人員財產申報資料專刊第四八期 </P>

<P>
<Ruby>
<RB>戶筒</RB>

<RT>SaF </RT>
</Ruby>
</P>

<P>R</P>

<P>總</P>

<P>噸</P>

<P>數</P>

<P>師指</P>

<P>籍</P>

<P>港</P>

<P>所</P>

<P>有</P>

<P>，在~</P>

<P>種類汽缸廿量牌照、號碼所有人普通小自客1,597cc MF4471 吳麗利 </P>

<P>-o</P>

<P>製造廠名幸存|國籍標示及編號|所有</P>

<P>一三五 </P>

<P>(五)存款(總金額:1,875 ,936 元)</P>

<P>1.新臺幣存款</P>

<P>監察院公報公職人員財產申報資料專刊第四八期 一三五一一 </P>

<Table>
<TR>
<TD>種類</TD>

<TD>存放機構</TD>

<TD>戶名</TD>

<TD>金</TD>

<TD>額</TD>
</TR>

<TR>
<TD>活期儲蓄</TD>

<TD>台灣中小企業銀行</TD>

<TD>陳超明 </TD>

<TD/>

<TD>46 ,185 </TD>
</TR>

<TR>
<TD>活儲</TD>

<TD>新竹企銀</TD>

<TD>陳超明 </TD>

<TD/>

<TD>32 ,416 </TD>
</TR>

<TR>
<TD>活儲</TD>

<TD>新竹企銀</TD>

<TD>陳超明 </TD>

<TD/>

<TD>8,165 </TD>
</TR>

<TR>
<TD>活儲</TD>

<TD>亞太商銀</TD>

<TD>陳超明 </TD>

<TD/>

<TD>376 ,183 </TD>
</TR>

<TR>
<TD>活儲</TD>

<TD>竹信</TD>

<TD>陳超明 </TD>

<TD/>

<TD>537 ,843 </TD>
</TR>

<TR>
<TD>活儲</TD>

<TD>彰化銀行</TD>

<TD>陳超明 </TD>

<TD/>

<TD>355 ,170 </TD>
</TR>

<TR>
<TD>活儲</TD>

<TD>竹南鎮農會</TD>

<TD>陳超明 </TD>

<TD/>

<TD>114 ,699 </TD>
</TR>

<TR>
<TD>活儲</TD>

<TD>土地銀行</TD>

<TD>陳超明 </TD>

<TD/>

<TD>428 </TD>
</TR>

<TR>
<TD>活儲</TD>

<TD>合作金庫</TD>

<TD>陳超明 </TD>

<TD/>

<TD>317 ,201 </TD>
</TR>

<TR>
<TD>活儲</TD>

<TD>華南銀行</TD>

<TD>陳超明 </TD>

<TD/>

<TD>77 ,812 </TD>
</TR>

<TR>
<TD>活儲</TD>

<TD>竹南信用合作社</TD>

<TD>吳麗利 </TD>

<TD/>

<TD>5,922 </TD>
</TR>

<TR>
<TD>活儲</TD>

<TD>第一商業銀行</TD>

<TD>陳超明 </TD>

<TD/>

<TD>3,912 </TD>
</TR>
</Table>

<P>2.外幣及其他帶別存款</P>

<Table>
<TR>
<TH>種類</TH>

<TH>幣</TH>

<TH>別存放機構</TH>

<TH>戶名</TH>

<TH>金額</TH>
</TR>

<TR>
<TD>折合新臺幣價額</TD>
</TR>

<TR>
<TH>無 </TH>

<TD/>

<TD>._____ </TD>

<TD/>

<TD/>
</TR>
</Table>

<P>(六)外幣(指現金或旅行支票)(總價額:元)</P>

<Table>
<TR>
<TH>|幣別|所有人|金</TH>

<TH>額|折合新臺幣價額| </TH>
</TR>

<TR>
<TH>|無 </TH>

<TD>I </TD>

<TD>I </TD>

<TD/>
</TR>

<TR>
<TH>(七)有價證券(股票、票券、債券及其他有價證券總價額1.股票(總價額: 18 ,070 ,500 元)</TH>

<TD>18， 070， 500</TD>

<TD>元)</TD>
</TR>
</Table>

<P>種類所有人股數票面價額總額</P>

<P>所羅門(股)公司陳超明1,807 ,050 10 18 ,070 ,500 </P>

<P>所 </P>

<P>2.票券(總價額:</P>

<P>da?EH 有人|單位數| </P>

<P>|| </P>

<P>3.債券(總價額:有 </P>

<P>人|單位數|</P>

<P>第四八期一三五三一</P>

<P>監察院公報</P>

<P>公職人員財產申報資料專刊</P>

<P>金</P>

<P>址</P>

<Part>
<H1>收士</H1>

<P>1 </P>

<P>產種類有</P>

<P>元一持一</P>

<P>元)</P>

<P>一單一一</P>

<P>人一一</P>

<P>，作</P>

<P>1</P>

<P>、 </P>

<P>，</P>

<P>類</P>

<P>ll )1 </P>

<P>有</P>

<P>vh'</P>

<P>吐.其他有價證券(總價額:</P>

<P>權務人及地</P>
</Part>

<Part>
<H1>士 </H1>

<P>149 , 876 , 220 元)</P>

<Table>
<TR>
<TD>種類</TD>

<TD>債務人</TD>

<TD>債權人及地拖上</TD>

<TD>金</TD>

<TD>額</TD>
</TR>

<TR>
<TD>抵押借款</TD>

<TD>陳超明</TD>

<TD>第苗一栗縣商業竹銀南行鎮中山路 </TD>

<TD/>

<TD>4, 776 , 220 </TD>
</TR>

<TR>
<TD>信用借款</TD>

<TD>陳超明</TD>

<TD>華苗栗南市商業銀行 </TD>

<TD/>

<TD>10 , 000 , 000 </TD>
</TR>

<TR>
<TD>信用借款</TD>

<TD>陳超明</TD>

<TD>合苗作栗金縣庫頭份鎮仁愛路70號 </TD>

<TD/>

<TD>15 , 000 , 000 </TD>
</TR>

<TR>
<TD>信用借款</TD>

<TD>陳超明</TD>

<TD>彰苗化栗銀市行 </TD>

<TD/>

<TD>30 , 000 , 000 </TD>
</TR>

<TR>
<TD>抵押借款</TD>

<TD>陳超明</TD>

<TD>亞台太北商市業敦銀化行南路l段325號 </TD>

<TD/>

<TD>8, 000 , 000 </TD>
</TR>

<TR>
<TD>信用借款</TD>

<TD>陳超明</TD>

<TD>亞台太北商市業敦銀化行南路l段325號 </TD>

<TD/>

<TD>9, 000 , 000 I </TD>
</TR>

<TR>
<TD>抵押借款</TD>

<TD>陳超明</TD>

<TD>新苗竹栗企市銀中正路562號 </TD>

<TD/>

<TD>6, 000 , 000 </TD>
</TR>

<TR>
<TD>信用借款</TD>

<TD>陳超明</TD>

<TD>新苗竹栗企市銀中正路562號 </TD>

<TD/>

<TD>2, 000 , 000 </TD>
</TR>

<TR>
<TD>抵押借款</TD>

<TD>陳超明</TD>

<TD>土頭地份銀鎮行 </TD>

<TD/>

<TD>8, 400 , 000 </TD>
</TR>

<TR>
<TD>信用借款</TD>

<TD>陳超明</TD>

<TD>土頭地份銀鎮行 </TD>

<TD/>

<TD>2, 000 , 000 </TD>
</TR>

<TR>
<TD>抵押借款</TD>

<TD>陳超明</TD>

<TD>苗苗栗栗縣縣竹竹南南鎮鎮農光會惺路 </TD>

<TD/>

<TD>12 , 700 , 000 </TD>
</TR>

<TR>
<TD>信用借款</TD>

<TD>陳超明</TD>

<TD>苗台灣栗縣中小竹企南銀鎮博愛街29號 </TD>

<TD/>

<TD>10 , 000 , 000 </TD>
</TR>
</Table>

<P>監察院公報公職人員財產申報資料專刊第四八期一三五二二</P>

<Table>
<TR>
<TD>抵押借款</TD>

<TD>陳超明</TD>

<TD>竹苗南栗信縣用竹合南作鎮社民族街87號 </TD>

<TD>23 ,000 ,000 I </TD>
</TR>

<TR>
<TD>信用借款</TD>

<TD>陳超明</TD>

<TD>竹苗栗南信縣用竹合南作鎮社民族街87號</TD>

<TD>民 000， 00</TD>
</TR>
</Table>

<P>臼事業投資(總金額:51 ,250 ,500 元)</P>

<Table>
<TR>
<TD>投資人</TD>

<TD>投資事業名稱及地 ;I:Jl:. </TD>

<TD>投資金額</TD>
</TR>

<TR>
<TD>陳超明</TD>

<TD>平苗順栗混縣凝造土橋股鄉份龍昇有村限公4鄰司47-1號 </TD>

<TD>26 ,500 ,000 </TD>
</TR>

<TR>
<TD>陳超明</TD>

<TD>捷苗栗茂縣開竹發南建鎮設股照份南里有光限復公路司 166號 </TD>

<TD>2,000 ,000 </TD>
</TR>

<TR>
<TD>陳超明</TD>

<TD>所台北羅市門南股港份有路3限段公47司巷2號 </TD>

<TD>18 ,070 ,500 </TD>
</TR>

<TR>
<TD>陳超明</TD>

<TD>國際建材工業股份有限公司 </TD>

<TD>4,680 ,000 </TD>
</TR>
</Table>

<P>包備註</P>

<P>無</P>

<P>此致監察院</P>

<P>(受理申報機關〔構〕全稱)以上資料，本人係依法誠實申報，如有不實，願負法律責任。</P>

<P>申報人:陳超明申報日期: 85年 12月 26日</P>
</Part>
</TaggedPDF-doc>
