<?xml version="1.0" encoding="UTF-8" ?>
<!-- Created from PDF via Acrobat SaveAsXML -->
<!-- Mapping Table version: 28-February-2003 -->
<TaggedPDF-doc>
<?xpacket begin='﻿' id='W5M0MpCehiHzreSzNTczkc9d'?>
<?xpacket begin="﻿" id="W5M0MpCehiHzreSzNTczkc9d"?>
<x:xmpmeta xmlns:x="adobe:ns:meta/" x:xmptk="Adobe XMP Core 5.4-c005 78.147326, 2012/08/23-13:03:03        ">
   <rdf:RDF xmlns:rdf="http://www.w3.org/1999/02/22-rdf-syntax-ns#">
      <rdf:Description rdf:about=""
            xmlns:xmp="http://ns.adobe.com/xap/1.0/"
            xmlns:dc="http://purl.org/dc/elements/1.1/"
            xmlns:xmpMM="http://ns.adobe.com/xap/1.0/mm/"
            xmlns:pdf="http://ns.adobe.com/pdf/1.3/">
         <xmp:ModifyDate>2007-11-06T15:45:19+08:00</xmp:ModifyDate>
         <xmp:CreateDate>2007-11-06T15:45:02+08:00</xmp:CreateDate>
         <xmp:MetadataDate>2007-11-06T15:45:19+08:00</xmp:MetadataDate>
         <xmp:CreatorTool>Adobe Acrobat 7.08</xmp:CreatorTool>
         <dc:format>xml</dc:format>
         <xmpMM:DocumentID>uuid:a652e6b8-10d4-4f25-8d72-04a207d8842d</xmpMM:DocumentID>
         <xmpMM:InstanceID>uuid:5b6c9888-799d-4fc2-9764-88088e1192a0</xmpMM:InstanceID>
         <pdf:Producer>Adobe Acrobat Pro 11.0.0 Paper Capture Plug-in</pdf:Producer>
      </rdf:Description>
   </rdf:RDF>
</x:xmpmeta>
                                                                                                    
                                                                                                    
                                                                                                    
                                                                                                    
                                                                                                    
                                                                                                    
                                                                                                    
                                                                                                    
                                                                                                    
                                                                                                    
                                                                                                    
                                                                                                    
                                                                                                    
                                                                                                    
                                                                                                    
                                                                                                    
                                                                                                    
                                                                                                    
                                                                                                    
                                                                                                    
                           
<?xpacket end="w"?>
<?xpacket end='r'?>

<P>I手、職 員財產申報表</P>

<P>品2、</P>

<Part>
<H2>人</H2>

<Table>
<TR>
<TH>申報人姓名</TH>

<TH>林叔宏</TH>

<TH>服務機關</TH>

<TH>1.國民大會2. </TH>

<TH/>

<TH>職稱 </TH>

<TH>1.國大代表</TH>
</TR>

<TR>
<TD>2. </TD>
</TR>

<TR>
<TH>商己偶</TH>

<TD>及未成年子</TD>

<TD>女</TD>

<TD>面已偶及</TD>

<TD>未成</TD>

<TD>年子女</TD>
</TR>

<TR>
<TH>稱</TH>

<TD>謂</TD>

<TD>姓</TD>

<TD>名</TD>

<TD>稱</TD>

<TD>謂</TD>

<TD>姓</TD>

<TD>名</TD>
</TR>

<TR>
<TH>妻</TH>

<TD/>

<TD>邱麗娜</TD>

<TD/>

<TD>女</TD>

<TD/>

<TD>林庭安</TD>

<TD/>
</TR>
</Table>

<P>(一)不動產</P>

<P>1.土地</P>

<Table>
<TR>
<TH>土地坐落</TH>

<TH>面(平方公尺積) </TH>

<TH>權利範園(持分)</TH>

<TH>所有權人</TH>
</TR>

<TR>
<TH>台中縣大里市內新段385-7地號 </TH>

<TD>210 </TD>

<TD>所有權全部</TD>

<TD>林叔宏</TD>
</TR>

<TR>
<TH>台中縣大里市內新段385一 10地號 </TH>

<TD>67 </TD>

<TD>所有權全部</TD>

<TD>林叔宏</TD>
</TR>

<TR>
<TH>台中縣大里市大里段 1646地號 </TH>

<TD>654.06 </TD>

<TD>65406分之5477</TD>

<TD>林叔宏</TD>
</TR>

<TR>
<TH>台中縣大里市向學段680地號 </TH>

<TD>31. 11 </TD>

<TD>15分之1</TD>

<TD>林叔宏</TD>
</TR>

<TR>
<TH>台中縣大里市向學段230， 227， 228地號 </TH>

<TD>90.21 </TD>

<TD>4分之l</TD>

<TD>邱麗娜</TD>
</TR>

<TR>
<TH>台中縣烏日鄉螺潭段32地號 </TH>

<TD>2, 177 </TD>

<TD>900分之136</TD>

<TD>林叔宏</TD>
</TR>

<TR>
<TH>台中縣烏日鄉螺潭段32地號 </TH>

<TD>2,177 </TD>

<TD>36分之2</TD>

<TD>邱麗娜</TD>
</TR>

<TR>
<TH>台中縣外埔鄉大甲東段54-45地號 </TH>

<TD>74 </TD>

<TD>所有權全部</TD>

<TD>邱麗娜</TD>
</TR>

<TR>
<TH>台中縣外埔鄉大甲東段54-47地號 </TH>

<TD>65 </TD>

<TD>所有權全部</TD>

<TD>邱麗娜</TD>
</TR>

<TR>
<TH>台中縣外埔鄉大甲東段54-9地號 </TH>

<TD>73 </TD>

<TD>所有權全部</TD>

<TD>邱麗娜</TD>
</TR>

<TR>
<TH>台中縣外埔鄉大甲東段54-12地號 </TH>

<TD>75 </TD>

<TD>所有權全部</TD>

<TD>邱麗娜</TD>
</TR>

<TR>
<TH>台中縣外埔鄉大甲東段54-59地號 </TH>

<TD>75 </TD>

<TD>所有權全部</TD>

<TD>邱麗娜</TD>
</TR>

<TR>
<TH>台中縣外埔鄉大甲東段54-61地號 </TH>

<TD>75 </TD>

<TD>所有權全部</TD>

<TD>邱麗娜</TD>
</TR>

<TR>
<TH>台中縣外埔鄉大甲東段54-62地號 </TH>

<TD>75 </TD>

<TD>所有權全部</TD>

<TD>邱麗娜</TD>
</TR>

<TR>
<TH>台中縣外埔鄉大甲東段54一個地號 </TH>

<TD>75 </TD>

<TD>所有權全部</TD>

<TD>邱麗娜</TD>
</TR>

<TR>
<TH>台中縣外埔鄉大甲東段54-28地號 </TH>

<TD>92 </TD>

<TD>所有權全部</TD>

<TD>邱麗娜</TD>
</TR>

<TR>
<TH>台中縣外埔鄉大甲東段54一切地號 </TH>

<TD>75 </TD>

<TD>所有權全部</TD>

<TD>邱麗娜</TD>
</TR>

<TR>
<TH>台中縣外埔鄉大甲東段54-31地號 </TH>

<TD>75 </TD>

<TD>所有權全部</TD>

<TD>邱麗娜</TD>
</TR>

<TR>
<TH>台中縣外埔鄉大甲東段54-32地號 </TH>

<TD>75 </TD>

<TD>所有權全部</TD>

<TD>邱麗娜</TD>
</TR>

<TR>
<TH>台中縣外埔鄉大甲東段54-33地號 </TH>

<TD>75 </TD>

<TD>所有權全部</TD>

<TD>邱麗娜</TD>
</TR>

<TR>
<TH>台中縣外埔鄉大甲東段54-34地號 </TH>

<TD>75 </TD>

<TD>所有權全部</TD>

<TD>邱麗娜</TD>
</TR>
</Table>

<P>監察院公報公職人員財產申報資料專刊第五六期一五八八二</P>

<P>監察院公報公職人員財產申報資料專刊第五六期</P>

<P>一五八八三</P>

<P>所有權全部</P>

<P>台中縣外埔鄉大甲東段54-77地號 </P>

<P>邱麗娜</P>

<P>97 </P>

<P>所有權全部</P>

<P>台中縣外埔鄉大甲東段54-81地號 </P>

<P>邱麗娜</P>

<P>22 </P>

<P>所有權全部</P>

<P>台中縣外埔鄉大甲東段54-86地號 </P>

<P>邱麗娜</P>

<P>30 </P>

<P>所有權全部</P>

<P>台中縣外埔鄉大甲東段54-89地號 </P>

<P>邱麗娜</P>

<P>264 </P>

<P>所有權全部</P>

<P>台中縣外埔鄉大甲東段54-88地號 </P>

<P>邱麗娜</P>

<P>53 </P>

<P>所有權全部</P>

<P>台中縣外埔鄉大甲東段54-87地號 </P>

<P>8 </P>

<P>邱麗娜</P>

<P>所有權全部</P>

<P>台中縣外埔鄉大甲東段54-54地號 </P>

<P>邱麗娜</P>

<P>64 </P>

<P>台中市西區後盧子段225-6地號 </P>

<P>邱麗娜</P>

<P>100000分之 1010</P>

<P>1, 544 </P>

<P>所有權全部</P>

<P>台中縣大里市鳳凰段 172-1地號 </P>

<P>83 </P>

<P>林叔宏 </P>

<P>2.房屋</P>

<Table>
<TR>
<TH>房屋 4票可Z</TH>

<TH>(面平方公尺積) </TH>

<TH>權利範園(持分)</TH>

<TH>所有權人 l</TH>
</TR>

<TR>
<TD>台中縣大里市大里段 1646地號建號2136 </TD>

<TD>194.80 </TD>

<TD>所有權全部</TD>

<TD>林叔宏</TD>
</TR>

<TR>
<TD>台中縣大里市向學段384， 385地號建號641 </TD>

<TD>205. 76 </TD>

<TD>所有權全部</TD>

<TD>邱麗娜</TD>
</TR>

<TR>
<TD>台中縣大里市向學段384， 385地號建號642 </TD>

<TD>204.60 </TD>

<TD>所有權全部</TD>

<TD>林叔宏</TD>
</TR>

<TR>
<TD>台中縣大里市向學段384， 385地號建號645 </TD>

<TD>207.02 </TD>

<TD>所有權全部</TD>

<TD>邱麗娜</TD>
</TR>

<TR>
<TD>台中縣大里市大里段 1646地號建號2155(車位)</TD>

<TD/>

<TD/>

<TD>林叔宏</TD>
</TR>

<TR>
<TD>台中市西區後嚨子段225-6地號建號 13069 </TD>

<TD>293.92 </TD>

<TD>所有權全部</TD>

<TD>邱麗娜</TD>
</TR>
</Table>

<P>總類</P>

<P>量</P>

<P>數</P>

<P>牌</P>

<P>船</P>

<P>~、</P>

<P>籍有</P>

<P>噸</P>
</Part>

<Part>
<H1>生
</H1>

<P>泊，</P>

<P>號碼有</P>
</Part>

<Part>
<H1>生
</H1>

<P>缸</P>

<P>。</P>

<P>製造廠名稱|國籍標示及編號|所有7, 760, 421 元) </P>

<P>人</P>

<P>種 報存放機構戶名金額定期存款合作金庫邱麗娜7, 180, 000 </P>

<Table>
<TR>
<TD>活儲存款</TD>

<TD>玉山銀行</TD>

<TD>邱麗娜 </TD>

<TD>59, 062 </TD>
</TR>

<TR>
<TD>活儲存款</TD>

<TD>玉山銀行</TD>

<TD>林叔宏 </TD>

<TD>122, 142 \ </TD>
</TR>

<TR>
<TD>活儲存款</TD>

<TD>第一銀行</TD>

<TD>林叔宏 </TD>

<TD>7, 301 </TD>
</TR>

<TR>
<TD>甲存</TD>

<TD>第一銀行</TD>

<TD>林叔宏 </TD>

<TD>697 </TD>
</TR>

<TR>
<TD>活儲存款</TD>

<TD>合作金庫</TD>

<TD>邱麗娜 </TD>

<TD>64, 409 </TD>
</TR>

<TR>
<TD>活儲存款</TD>

<TD>農民銀行</TD>

<TD>林叔宏 </TD>

<TD>1, 833 </TD>
</TR>

<TR>
<TD>活儲存款</TD>

<TD>農民銀行</TD>

<TD>林叔宏 </TD>

<TD>10, 368 </TD>
</TR>

<TR>
<TD>活儲存款</TD>

<TD>台中三信</TD>

<TD>林叔宏 </TD>

<TD>6, 278 </TD>
</TR>

<TR>
<TD>甲存</TD>

<TD>台中三信</TD>

<TD>林叔宏 </TD>

<TD>1, 027 </TD>
</TR>

<TR>
<TD>活儲存款</TD>

<TD>世華銀行</TD>

<TD>邱麗娜 </TD>

<TD>307, 304 </TD>
</TR>
</Table>

<P>2.外幣及其他幣別存款</P>

<Table>
<TR>
<TD>種類</TD>

<TD>幣別</TD>

<TD>存放機構</TD>

<TD>戶名</TD>

<TD>金額折合新臺幣價額</TD>
</TR>

<TR>
<TD>無</TD>

<TD/>

<TD/>

<TD/>

<TD/>
</TR>
</Table>

<P>(六)外幣(指現金或旅行支票)(總價額:元)</P>

<P>|幣別|所有人|金額|折合新臺幣價額| |無 I I </P>

<P>(七)有價證券(股票、票券、債券及其他有價證券總價額:2， 785， 000元)</P>

<L>
<LI>
<Lbl>1.股票(總價額: </Lbl>

<LBody>2, 735, 000 元)</LBody>
</LI>

<LI>
<Lbl>2.</Lbl>

<LBody>票券(總價額:</LBody>
</LI>
</L>

<Table>
<TR>
<TD>種類</TD>

<TD>所有人</TD>

<TD>月史</TD>

<TD>數</TD>

<TD>票面價額</TD>

<TD>總</TD>

<TD>額</TD>
</TR>

<TR>
<TD>泛亞銀行</TD>

<TD>林叔宏 </TD>

<TD/>

<TD>84, 000 </TD>

<TD>10 </TD>

<TD/>

<TD>840, 000 </TD>
</TR>

<TR>
<TD>馬上發國際股份有限公司</TD>

<TD>林叔宏 </TD>

<TD/>

<TD>67, 000 </TD>

<TD>10 </TD>

<TD/>

<TD>670, 000 </TD>
</TR>

<TR>
<TD>馬上發國際股份有限公司</TD>

<TD>林庭安 </TD>

<TD/>

<TD>80 , 000 </TD>

<TD>10 </TD>

<TD/>

<TD>800, 000 </TD>
</TR>

<TR>
<TD>台中三信</TD>

<TD>邱麗娜 </TD>

<TD/>

<TD>3, 000 </TD>

<TD>100 </TD>

<TD/>

<TD>300, 000 </TD>
</TR>

<TR>
<TD>興農人壽</TD>

<TD>邱麗娜 </TD>

<TD/>

<TD>10, 000 </TD>

<TD>10 </TD>

<TD/>

<TD>100, 000 </TD>
</TR>

<TR>
<TD>信益陶瓷</TD>

<TD>邱麗娜 </TD>

<TD/>

<TD>2, 500 </TD>

<TD>10 </TD>

<TD/>

<TD>25, 000 </TD>
</TR>
</Table>

<P>元一/-</P>

<P>一數一一一位一一一單一一</P>

<P>監察院公報公職人員財產申報資料專刊第五六期 一五八八四</P>

<P>持川</P>

<P>.缸
<Ruby>
<RB>，</RB>

<RT>1</RT>
</Ruby>
</P>

<P>類</P>

<P>有</P>

<P>、 、自』</P>

<P>1J'</P>

<P>票面價額</P>

<P>3.債券(總價額:</P>

<P>有</P>

<P>票面價額</P>

<P>監察院公報 公職人員財產申報資料專刊</P>

<P>第五六期一五八八五</P>

<Sect>
<H3>元一人一一。</H3>

<Sect>
<H3>人</H3>
</Sect>
</Sect>

<Sect>
<H2>一倆一一元
</H2>

<P>一單一一</P>
<Figure>

<ImageData src=""/>
</Figure>

<P>票面價額</P>

<P>總</P>

<P>額</P>

<P>10 50, 000 
</P>

<P>持川!</P>

<P>可缸，</P>

<P>類 </P>

<P>4.其他有價證券(總價額:</P>

<P>種 </P>

<P>類</P>

<P>所</P>

<P>有</P>

<P>京華三喜基金邱麗娜(八)其他財產</P>

<P>財 產種類所有人價額露峰高爾夫球證 林叔宏500, 000 </P>

<Table>
<TR>
<TH>金幣</TH>

<TH/>

<TH/>

<TH/>

<TH>邱麗娜</TH>

<TH/>

<TH/>

<TH/>

<TH>200, 000 </TH>
</TR>

<TR>
<TD>(九)債權(總金額:</TD>

<TD>元)</TD>

<TD/>

<TD/>

<TD/>

<TD/>

<TD/>

<TD/>
</TR>

<TR>
<TD>權|種類|債人</TD>

<TD>債白務 </TD>

<TD>人</TD>

<TD>及</TD>

<TD>正也</TD>

<TD>址</TD>

<TD>金</TD>

<TD/>
</TR>

<TR>
<TD>|無| </TD>

<TD/>

<TD/>

<TD/>

<TD/>

<TD/>

<TD/>

<TD/>

<TD/>
</TR>

<TR>
<TD/>

<TD/>

<TD>nunxu </TD>

<TD/>

<TD/>

<TD/>

<TD/>

<TD/>

<TD/>
</TR>

<TR>
<TD>( +)債務(總金額:</TD>

<TD>元)</TD>

<TD/>

<TD/>

<TD/>

<TD/>

<TD/>

<TD/>
</TR>

<TR>
<TD/>

<TD/>

<TD/>

<TD/>

<TD/>

<TD/>

<TD/>

<TD/>

<TD/>

<TD/>
</TR>

<TR>
<TD/>

<TD/>

<TD/>

<TD/>

<TD/>

<TD/>

<TD/>

<TD/>

<TD/>

<TD/>
</TR>

<TR>
<TD/>

<TD/>

<TD/>

<TD/>

<TD/>

<TD/>

<TD/>

<TD/>

<TD/>

<TD/>
</TR>

<TR>
<TD/>

<TD/>

<TD/>

<TD/>

<TD/>

<TD/>

<TD/>

<TD/>

<TD/>

<TD/>
</TR>

<TR>
<TD/>

<TD/>

<TD/>

<TD/>

<TD/>

<TD/>

<TD/>

<TD/>

<TD/>

<TD/>
</TR>

<TR>
<TD/>

<TD/>

<TD/>

<TD/>

<TD/>

<TD/>

<TD/>

<TD/>

<TD/>

<TD/>
</TR>

<TR>
<TD/>

<TD/>

<TD/>

<TD/>

<TD/>

<TD/>

<TD/>

<TD/>

<TD/>

<TD/>
</TR>

<TR>
<TD/>

<TD/>

<TD/>

<TD/>

<TD/>

<TD/>

<TD/>

<TD/>

<TD/>

<TD/>
</TR>
</Table>

<Table>
<TR>
<TD>種類</TD>

<TD/>

<TD>債務人</TD>

<TD>債權</TD>

<TD>人</TD>

<TD>及</TD>

<TD>地 </TD>

<TD>;hl_ </TD>

<TD>金</TD>

<TD>額</TD>
</TR>

<TR>
<TD/>

<TD/>

<TD/>

<TD/>

<TD/>

<TD/>

<TD/>

<TD/>

<TD/>

<TD/>
</TR>

<TR>
<TD>抵押貸款</TD>

<TD/>

<TD>林叔宏</TD>

<TD>台中大里農銀 </TD>

<TD/>

<TD/>

<TD/>

<TD/>

<TD/>

<TD>9, 300, 000 </TD>
</TR>

<TR>
<TD>抵押貸款</TD>

<TD/>

<TD>林叔宏</TD>

<TD>玉山銀行(大里) </TD>

<TD/>

<TD/>

<TD/>

<TD/>

<TD/>

<TD>16, 000, 000 </TD>
</TR>

<TR>
<TD>抵押貸款</TD>

<TD/>

<TD>林叔宏</TD>

<TD>第一銀行(大里) </TD>

<TD/>

<TD/>

<TD/>

<TD/>

<TD/>

<TD>5, 800, 000 </TD>
</TR>

<TR>
<TD>抵押貸款</TD>

<TD/>

<TD>林叔宏</TD>

<TD>台中泛亞銀行 </TD>

<TD/>

<TD/>

<TD/>

<TD/>

<TD/>

<TD>7, 900, 000 </TD>
</TR>

<TR>
<TD>抵押貸款</TD>

<TD/>

<TD>林叔宏</TD>

<TD>台中大里合庫 </TD>

<TD/>

<TD/>

<TD/>

<TD/>

<TD/>

<TD>4, 600, 000 </TD>
</TR>

<TR>
<TD>抵押貸款</TD>

<TD/>

<TD>邱麗娜</TD>

<TD>台中大里合庫 </TD>

<TD/>

<TD/>

<TD/>

<TD/>

<TD/>

<TD>9, 200, 000 </TD>
</TR>
</Table>

<P>t均事業投資(總金頻:14, 500, 000 元)</P>

<Table>
<TR>
<TH>投資人</TH>

<TH>投資事業名幸存及地 ;hl_ </TH>

<TH>投資金額</TH>
</TR>

<TR>
<TH>林叔宏</TH>

<TD>新林光園建路設9號股份有限公司 </TD>

<TD>3, 000, 000 </TD>
</TR>

<TR>
<TH>林叔宏</TH>

<TD>伯新仁園建路設2段股2份62有號限公司 </TD>

<TD>3, 000 , 000 </TD>
</TR>

<TR>
<TH>邱麗娜</TH>

<TD>璽新仁園建路設2段股2份62有號限公司 </TD>

<TD>6, 000 , 000 </TD>
</TR>

<TR>
<TH>林叔宏</TH>

<TD>永台雋中大營造里股愛份心有三街限公30號司 </TD>

<TD>2, 000, 000 </TD>
</TR>

<TR>
<TH>邱麗娜</TH>

<TD>永台雋中大營造旦股愛份心有三街限公30號司 </TD>

<TD>500, 000 </TD>
</TR>
</Table>

<P>包備註</P>

<P>無</P>

<P>ι&quot;F</P>

<P>致 </P>

<P>監察院</P>

<P>(受理申報機關〔構〕全稱)</P>

<P>以上資料，本人係依法誠實申報，如有不實，願負法律責任。</P>

<P>申</P>

<P>報人:林叔宏申報日期: 86年 12月 15日</P>

<P>監察院公報</P>

<P>公職人員財產申報資料專刊</P>

<P>第五六期一五八八六</P>
</Sect>
</Part>
</TaggedPDF-doc>
