<?xml version="1.0" encoding="UTF-8" ?>
<!-- Created from PDF via Acrobat SaveAsXML -->
<!-- Mapping Table version: 28-February-2003 -->
<TaggedPDF-doc>
<?xpacket begin='﻿' id='W5M0MpCehiHzreSzNTczkc9d'?>
<?xpacket begin="﻿" id="W5M0MpCehiHzreSzNTczkc9d"?>
<x:xmpmeta xmlns:x="adobe:ns:meta/" x:xmptk="Adobe XMP Core 5.4-c005 78.147326, 2012/08/23-13:03:03        ">
   <rdf:RDF xmlns:rdf="http://www.w3.org/1999/02/22-rdf-syntax-ns#">
      <rdf:Description rdf:about=""
            xmlns:xmp="http://ns.adobe.com/xap/1.0/"
            xmlns:dc="http://purl.org/dc/elements/1.1/"
            xmlns:xmpMM="http://ns.adobe.com/xap/1.0/mm/"
            xmlns:pdf="http://ns.adobe.com/pdf/1.3/">
         <xmp:ModifyDate>2007-11-13T16:13:49+08:00</xmp:ModifyDate>
         <xmp:CreateDate>2007-11-13T16:13:45+08:00</xmp:CreateDate>
         <xmp:MetadataDate>2007-11-13T16:13:49+08:00</xmp:MetadataDate>
         <xmp:CreatorTool>Adobe Acrobat 7.08</xmp:CreatorTool>
         <dc:format>xml</dc:format>
         <xmpMM:DocumentID>uuid:a5ff44b9-2232-48a8-995c-ddc9cdf910b3</xmpMM:DocumentID>
         <xmpMM:InstanceID>uuid:d3657b76-a49e-4d12-bdf8-c22a94d5ef53</xmpMM:InstanceID>
         <pdf:Producer>Adobe Acrobat Pro 11.0.0 Paper Capture Plug-in</pdf:Producer>
      </rdf:Description>
   </rdf:RDF>
</x:xmpmeta>
                                                                                                    
                                                                                                    
                                                                                                    
                                                                                                    
                                                                                                    
                                                                                                    
                                                                                                    
                                                                                                    
                                                                                                    
                                                                                                    
                                                                                                    
                                                                                                    
                                                                                                    
                                                                                                    
                                                                                                    
                                                                                                    
                                                                                                    
                                                                                                    
                                                                                                    
                                                                                                    
                           
<?xpacket end="w"?>
<?xpacket end='r'?>

<P>公職</P>

<P>員財產</P>

<Part>
<H2>人</H2>

<P>申</P>

<P>報表</P>

<Table>
<TR>
<TH>申報人姓名</TH>

<TH>余政憲</TH>

<TH>服務機關</TH>

<TH>1.高雄縣政府</TH>

<TH/>

<TH>職稱 </TH>

<TH>1.縣長</TH>
</TR>

<TR>
<TD/>

<TD/>

<TD/>

<TD>2. </TD>

<TD/>

<TD/>

<TD>2. </TD>
</TR>

<TR>
<TD>配偽及未成年子女</TD>

<TD/>

<TD>配偶及未成年子女</TD>
</TR>

<TR>
<TD>稱謂</TD>

<TD>!姓名</TD>

<TD>稱</TD>

<TD>謂</TD>

<TD>?蛀名</TD>
</TR>

<TR>
<TD>妻</TD>

<TD>鄭貴蓮</TD>

<TD>長女</TD>

<TD/>

<TD>余佳臻</TD>
</TR>

<TR>
<TD>次女</TD>

<TD>余佳縈</TD>

<TD>長子</TD>

<TD/>

<TD>余俊陸</TD>
</TR>
</Table>

<P>(一)不動產</P>

<P>1.土士也</P>

<Table>
<TR>
<TD>土 t也坐洛品爭</TD>

<TD>面積(平方公尺)</TD>

<TD>權利範園(持分)</TD>

<TD>所有權人</TD>
</TR>

<TR>
<TD>高雄縣大社鄉林子邊段5地號 </TD>

<TD>102 </TD>

<TD>6分之l</TD>

<TD>余政憲</TD>
</TR>

<TR>
<TD>高雄縣大社鄉林子邊段5-H也號 </TD>

<TD>1,193 </TD>

<TD>6分之 l</TD>

<TD>余政憲</TD>
</TR>

<TR>
<TD>高雄縣大社鄉林子邊段6地號 </TD>

<TD>16 </TD>

<TD>6分之 l</TD>

<TD>余政憲</TD>
</TR>

<TR>
<TD>高雄縣大社鄉林子邊段6-2地號 </TD>

<TD>3,325 </TD>

<TD>6分之l</TD>

<TD>余政憲</TD>
</TR>

<TR>
<TD>高雄縣大社鄉林子邊段 10-1地號 </TD>

<TD>1,639 </TD>

<TD>6分之 l</TD>

<TD>余政憲</TD>
</TR>

<TR>
<TD>高雄縣大社鄉林子邊段 10-2地號 </TD>

<TD>3,715 </TD>

<TD>6分之1</TD>

<TD>余政憲</TD>
</TR>

<TR>
<TD>高雄縣大社鄉林子邊段 10-4地號 </TD>

<TD>3,424 </TD>

<TD>6分之 l</TD>

<TD>余政憲</TD>
</TR>

<TR>
<TD>高雄縣大社鄉林子邊段22地號 </TD>

<TD>1,659 </TD>

<TD>6分之l</TD>

<TD>余政憲</TD>
</TR>

<TR>
<TD>高雄縣大社鄉林子邊段24地號 </TD>

<TD>495 </TD>

<TD>6分之l</TD>

<TD>余政憲</TD>
</TR>

<TR>
<TD>高雄縣大社鄉林子邊段24-2地號 </TD>

<TD>1,484 </TD>

<TD>6分之l</TD>

<TD>余政憲</TD>
</TR>

<TR>
<TD>高雄縣大社鄉林子邊段26地號 </TD>

<TD>3,417 </TD>

<TD>6分之l</TD>

<TD>余政憲</TD>
</TR>

<TR>
<TD>高雄縣大社鄉林子邊段26-1地號 </TD>

<TD>46 </TD>

<TD>6分之l</TD>

<TD>余政憲</TD>
</TR>

<TR>
<TD>高雄縣大社鄉林子邊段27地號 </TD>

<TD>4,214 </TD>

<TD>6分之l</TD>

<TD>余政憲</TD>
</TR>

<TR>
<TD>高雄縣大社鄉林子邊段訝地號 </TD>

<TD>1,482 </TD>

<TD>6分之l</TD>

<TD>余政憲</TD>
</TR>

<TR>
<TD>高雄縣大社鄉林子邊段29-1地號 </TD>

<TD>12 </TD>

<TD>6分之l</TD>

<TD>余政憲</TD>
</TR>

<TR>
<TD>高雄縣大社鄉林子邊段30地號 </TD>

<TD>509 </TD>

<TD>6分之 l</TD>

<TD>余政憲</TD>
</TR>

<TR>
<TD>高雄縣大社鄉林子邊段訕地號 </TD>

<TD>1, 101 </TD>

<TD>6分之l</TD>

<TD>余政憲</TD>
</TR>

<TR>
<TD>高雄縣大社鄉林子邊段35地號 </TD>

<TD>1,594 </TD>

<TD>6分之l</TD>

<TD>余政憲</TD>
</TR>

<TR>
<TD>高雄縣大社鄉林子邊段35-1Þ世號 </TD>

<TD>486 </TD>

<TD>6分之 l</TD>

<TD>余政憲</TD>
</TR>

<TR>
<TD>高雄縣大社鄉林子邊段36地號 </TD>

<TD>1,431 </TD>

<TD>6分之l</TD>

<TD>余政憲</TD>
</TR>
</Table>

<P>監察院公報公職人員財產申報資料專刊第九二期八八</P>

<P>監察院公報公職人員財產申報資料專刊第九二期</P>

<P>八</P>

<P>九</P>

<Table>
<TR>
<TH>高雄縣大社鄉林子邊段36-1地號 </TH>

<TH>320 </TH>

<TH>6分之l</TH>

<TH>余政憲</TH>
</TR>

<TR>
<TH>高雄縣大社鄉林子邊段37地號 </TH>

<TD>1,579 </TD>

<TD>6分之 l</TD>

<TD>余政憲</TD>
</TR>

<TR>
<TH>高雄縣大社鄉林子邊段37-1地號 </TH>

<TD>225 </TD>

<TD>6分之 l</TD>

<TD>余政憲</TD>
</TR>

<TR>
<TH>高雄縣大社鄉林子邊段38地號 </TH>

<TD>1,924 </TD>

<TD>6分之 l</TD>

<TD>余政憲</TD>
</TR>

<TR>
<TH>高雄縣大社鄉林子邊段38-1:[:也號 </TH>

<TD>336 </TD>

<TD>6分之 l</TD>

<TD>余政憲</TD>
</TR>

<TR>
<TH>高雄縣大社鄉林子邊段的地號 </TH>

<TD>2,153 </TD>

<TD>6分之 l</TD>

<TD>余政憲</TD>
</TR>

<TR>
<TH>高雄縣大社鄉林子邊段42地號 </TH>

<TD>3,385 </TD>

<TD>6分之 l</TD>

<TD>余政憲</TD>
</TR>

<TR>
<TH>高雄縣大社鄉林子邊段 H也號 </TH>

<TD>100 </TD>

<TD>12分之 l</TD>

<TD>余政憲</TD>
</TR>

<TR>
<TH>高雄縣大社鄉林子邊段 1-6地號 </TH>

<TD>1,898 </TD>

<TD>12分之 l</TD>

<TD>余政憲</TD>
</TR>

<TR>
<TH>高雄縣大社鄉林子邊段 1-7地號 </TH>

<TD>155 </TD>

<TD>12分之l</TD>

<TD>余政憲</TD>
</TR>

<TR>
<TH>高雄縣大社鄉林子邊段 1-8地號 </TH>

<TD>42 </TD>

<TD>12分之l</TD>

<TD>余政憲</TD>
</TR>

<TR>
<TH>高雄縣大社鄉林子邊段 1-361地號 </TH>

<TD>1,015 </TD>

<TD>12分之l</TD>

<TD>余政憲</TD>
</TR>

<TR>
<TH>高雄縣大社鄉林子邊段8地號 </TH>

<TD>7,885 </TD>

<TD>6分之l</TD>

<TD>余政憲</TD>
</TR>

<TR>
<TH>高雄縣大社鄉林子邊段 10地號 </TH>

<TD>2,653 </TD>

<TD>6分之l</TD>

<TD>余政憲</TD>
</TR>

<TR>
<TH>高雄縣大社鄉林子邊段 10-3地號 </TH>

<TD>436 </TD>

<TD>6分之 l</TD>

<TD>余政憲</TD>
</TR>

<TR>
<TH>高雄縣大社鄉林子邊段28地號 </TH>

<TD>58 </TD>

<TD>6分之l</TD>

<TD>余政憲</TD>
</TR>

<TR>
<TH>高雄縣大社鄉林子邊段28-5地號 </TH>

<TD>194 </TD>

<TD>6分之l</TD>

<TD>余政憲</TD>
</TR>

<TR>
<TH>高雄縣大社鄉三奶壇段4-9地號 </TH>

<TD>320 </TD>

<TD>53672分之6663</TD>

<TD>余政憲</TD>
</TR>

<TR>
<TH>高雄縣大社鄉三奶壇段4-35地號 </TH>

<TD>160 </TD>

<TD>53672分之6663</TD>

<TD>余政憲</TD>
</TR>

<TR>
<TH>高雄縣大社鄉三奶壇段4-36地號 </TH>

<TD>134 </TD>

<TD>53672分之6663</TD>

<TD>余政憲</TD>
</TR>

<TR>
<TH>高雄縣大社鄉三奶壇段4-37地號 </TH>

<TD>257 </TD>

<TD>12分之1</TD>

<TD>余政憲</TD>
</TR>

<TR>
<TH>高雄縣大社鄉三奶壇段4-38地號 </TH>

<TD>22 </TD>

<TD>12分之 l</TD>

<TD>余政憲</TD>
</TR>

<TR>
<TH>高雄縣大社鄉三奶壇段4-39地號 </TH>

<TD>726 </TD>

<TD>10000分之553</TD>

<TD>余政憲</TD>
</TR>

<TR>
<TH>高雄縣大社鄉三奶壇段4-40地號 </TH>

<TD>1,610 </TD>

<TD>12分之 l</TD>

<TD>余政憲</TD>
</TR>

<TR>
<TH>高雄縣大社鄉三奶壇段4-41地號 </TH>

<TD>800 </TD>

<TD>100000分之8295 </TD>

<TD>余政憲 </TD>
</TR>

<TR>
<TH>高雄縣大社鄉三奶壇段4-43地號 </TH>

<TD>1,291 </TD>

<TD>2分之l</TD>

<TD>余政憲</TD>
</TR>

<TR>
<TH>高雄縣大社鄉三奶壇段4-45地號 </TH>

<TD>1,061 </TD>

<TD>2分之 l</TD>

<TD>余政憲</TD>
</TR>

<TR>
<TH>高雄縣大社鄉三奶壇段4-46地號 </TH>

<TD>3,784 </TD>

<TD>2分之l</TD>

<TD>余政憲</TD>
</TR>

<TR>
<TH>高雄縣大社鄉三奶壇段4-51地號 </TH>

<TD>2,570 </TD>

<TD>10000分之 1659</TD>

<TD>余政憲</TD>
</TR>
</Table>

<P>高雄縣大社鄉三奶壇段4-52地號 </P>

<P>40 </P>

<P>10000分之 1659</P>

<P>余政憲</P>

<P>高雄縣大社鄉三奶壇段4-53地號 </P>

<P>余政憲</P>

<P>90 </P>

<P>高雄縣大社鄉三奶壇段4-54地號 </P>

<P>10000分之 1659</P>

<P>149 </P>

<P>余政憲</P>

<P>高雄縣大社鄉三奶壇段4-55地號 </P>

<P>14 </P>

<P>10000分之 1659</P>

<P>余政憲</P>

<P>高雄縣大社鄉三奶壇段4-56地號 </P>

<P>71 </P>

<P>2分之l</P>

<P>余政憲</P>

<P>高雄縣大社鄉三奶壇段4-57地號 </P>

<P>2分之l</P>

<P>余政憲</P>

<P>63 </P>

<P>高雄縣大社鄉三奶壇段4-61地號 </P>

<P>余政憲</P>

<P>91 100000分之829</P>

<P>5 </P>

<P>高雄縣大社鄉三奶壇段4-62地號 </P>

<P>余政憲</P>

<P>33 </P>

<P>4分之 l</P>

<P>高雄縣大社鄉三奶壇段4-63地號 </P>

<P>余政憲</P>

<P>26 </P>

<P>2分之l</P>

<P>高雄縣大社鄉三奶壇段4-66地號 </P>

<P>6153672分之6663</P>

<P>余政憲</P>

<P>高雄縣大社鄉三奶壇段4-67地號 </P>

<P>余政憲</P>

<P>2153672分之6663</P>

<P>高雄縣大社鄉三奶壇段4-68地號 </P>

<P>余政憲</P>

<P>2153672分之6663</P>

<P>高雄縣大社鄉三奶壇段4-71地號 </P>

<P>余政憲</P>

<P>81 10000分之3341</P>

<P>高雄縣大社鄉三奶壇段4-81地號 </P>

<P>74 </P>

<P>53672分之6663</P>

<P>余政憲</P>

<P>高雄縣大社鄉三奶壇段4-82地號 </P>

<P>余政憲</P>

<P>3153672分之6663</P>

<P>高雄縣大社鄉三奶壇段205地號 </P>

<P>余政憲</P>

<P>6分之l</P>

<P>2,562 </P>

<P>高雄縣大社鄉三奶壇段205-1地號 </P>

<P>348 </P>

<P>3分之l</P>

<P>余政憲</P>

<P>高雄縣大社鄉三奶壇段208-1地號 </P>

<P>3分之 l</P>

<P>余政憲</P>

<P>1,246 </P>

<P>高雄縣大社鄉了奶壇段 1135-2地號 </P>

<P>18分之l</P>

<P>余政憲</P>

<P>207 </P>

<P>高雄縣大社鄉保舍甲段546-4地號 </P>

<P>余政憲</P>

<P>5014分之972</P>

<P>3,755 </P>

<P>高雄縣大社鄉保舍甲段546-的也號 </P>

<P>6分之1</P>

<P>478 </P>

<P>余政憲</P>

<P>高雄縣大社鄉保舍甲段546-13地號 </P>

<P>674 </P>

<P>2分之l</P>

<P>余政憲</P>

<P>高雄縣大社鄉保舍甲段546-14地號 </P>

<P>25 </P>

<P>6分之l</P>

<P>余政憲</P>

<P>所有權全部</P>

<P>高雄縣大社鄉保舍甲段546-265地號 </P>

<P>826 </P>

<P>余政憲</P>

<P>高雄縣大社鄉保舍甲段555地號 </P>

<P>739 </P>

<P>24分之5</P>

<P>余政憲</P>

<P>高雄縣大社鄉保舍甲段555-3地號 </P>

<P>146 </P>

<P>24分之5</P>

<P>余政憲</P>

<P>高雄縣大社鄉保舍甲段559-2地號 </P>

<P>24分之5</P>

<P>余政憲</P>

<P>4,573 </P>

<P>局雄縣仁武鄉八德段200地號</P>

<P>3分之l</P>

<P>905.94 </P>

<P>余政憲</P>

<P>高雄縣仁武鄉八德段230地號 </P>

<P>余政憲</P>

<P>304.60 </P>

<P>3分之l</P>

<P>監察院公報公職人員財產申報資料專刊第九二期</P>

<P>九</P>

<Sect>
<H2>。</H2>

<P>監察院公報公職人員財產申報資料專刊第九二期 </P>

<Table>
<TR>
<TD>高雄縣仁武鄉八德段232地號 高雄縣仁武鄉八德段240地號 高雄縣仁武鄉八德段241地號 高雄縣仁武鄉八德段293地號 高雄縣仁武鄉八德段294地號 高雄縣仁武鄉八德段313地號 高雄縣仁武鄉八德段314地號 高雄縣仁武鄉八德段314-1地號 </TD>

<TD>55.45 1,012.87 503.96 360.41 102.13 82.85 84.26 1. 18 </TD>

<TD>3分之 l所有權全部所有權全部3分之 l43241分之73643241分之73643241分之73643241分之736</TD>

<TD>余政憲余政憲余政憲余政憲余政憲余政憲余政憲余政憲</TD>
</TR>

<TR>
<TD>高雄縣仁武鄉後港段的地號 高雄縣仁武鄉後港段84地號 高雄縣仁武鄉後港段的地號 高雄縣永安鄉竹子港段624-6t也號 高雄縣永安鄉竹子港段624-8地號 高雄縣永安鄉竹子港段687-1地號 高雄縣永安鄉竹子港段687-2地號 高雄縣永安鄉竹子港段704-6地號 高雄縣永安鄉竹子港段851-1地號 高雄縣橋頭鄉橋北段 1134地號 高雄縣橋頭鄉橋北段 1214地號 高雄縣橋頭鄉橋北段 1239地號 高雄縣橋頭鄉興樹段555地號 高雄縣橋頭鄉興樹段560地號 高雄縣鳥松鄉育才段248地號 </TD>

<TD>115.06 34.08 200.71 97 154 87 160 48 616 574 10 138 75.57 40.40 6,428 </TD>

<TD>6分之36分之36分之33分之l3分之l3分之l3分之 l18分之4269260分之 13157 269720分之2702分之l2分之l所有權全部6分之 l10000分之 127</TD>

<TD>余政憲余政憲余政憲余政憲余政憲余政憲余政憲余政憲余政憲 余政憲余政憲余政憲余政憲余政憲鄭貴蓮</TD>
</TR>
</Table>

<P>2.房屋房屋標訂τ</P>

<P>高雄縣橋頭鄉橋南路27號(未登記建物) 高雄縣橋頭鄉興樹段555地號建號78 高雄縣鳥松鄉育才段248地號建號 1228 </P>

<P>九</P>

<P>面積</P>

<P>(平方公尺)</P>

<P>190.10 </P>

<P>156.96 </P>

<P>239.70 </P>

<Table>
<TR>
<TD>權利範園(持分)</TD>

<TD>所有權人</TD>
</TR>

<TR>
<TD>2分之 l所有權全部所有權全部</TD>

<TD>余政憲余政憲鄭貴蓮</TD>
</TR>
</Table>

<P>總類</P>

<P>噸</P>

<P>船數</P>

<P>籍</P>

<P>港</P>

<P>4戶，</P>

<P>有</P>

<Sect>
<H3>丹-滅</H3>

<P>何</P>

<P>EA-Z </P>

<P>造廠名稱|國籍標示及編號|所有人</P>
</Sect>
</Sect>
</Part>

<Part>
<H1>人|星
</H1>

<P>院公</P>
<Figure>

<ImageData src=""/>
</Figure>

<P>,,</P>

<P>碼一號一</P>

<P>一客一四一種一小一(一型 </P>

<P>無</P>

<Sect>
<H3>一車一流一</H3>

<P>報</P>

<P>類|汽量|牌</P>

<P>有</P>

<P>缸容 </P>

<P>日哥</P>

<P>憲</P>

<P>2199 VN8888 
</P>

<P>公職人員財產申報資料專刊第九二期</P>

<P>製式</P>

<P>器一</P>

<P>(五)存款(總金額:1, 852， 261元)</P>

<L>
<LI>
<Lbl>1.</Lbl>

<LBody>新台幣存款 </LBody>
</LI>

<LI>
<Lbl>2.</Lbl>

<LBody>外幣及其他幣別存款</LBody>
</LI>
</L>

<Table>
<TR>
<TD>種類</TD>

<TD>存放機構</TD>

<TD>戶名</TD>

<TD>金</TD>

<TD>額</TD>
</TR>

<TR>
<TD>存簿存款</TD>

<TD>郵局</TD>

<TD>余政憲 </TD>

<TD/>

<TD>1,416 ,481 </TD>
</TR>

<TR>
<TD>存簿存款</TD>

<TD>郵局</TD>

<TD>鄭貴蓮 </TD>

<TD/>

<TD>2, 669 </TD>
</TR>

<TR>
<TD>支票存款</TD>

<TD>彰化商業銀行</TD>

<TD>余政憲 </TD>

<TD/>

<TD>286 </TD>
</TR>

<TR>
<TD>支票存款</TD>

<TD>彰化商業銀行</TD>

<TD>鄭貴蓮</TD>

<TD/>

<TD>。</TD>
</TR>

<TR>
<TD>活期存款</TD>

<TD>彰化商業銀行</TD>

<TD>余俊陸 </TD>

<TD/>

<TD>5, 249 </TD>
</TR>

<TR>
<TD>活期存款</TD>

<TD>彰化商業銀行</TD>

<TD>余佳臻 </TD>

<TD/>

<TD>43 , 532 </TD>
</TR>

<TR>
<TD>活期存款</TD>

<TD>彰化商業銀行</TD>

<TD>余佳縈 </TD>

<TD/>

<TD>46 , 765 </TD>
</TR>

<TR>
<TD>綜合存款</TD>

<TD>華南商業銀行</TD>

<TD>鄭貴蓮 </TD>

<TD/>

<TD>24 , 224 </TD>
</TR>

<TR>
<TD>活期存款</TD>

<TD>彰化商業銀行</TD>

<TD>鄭貴蓮 </TD>

<TD/>

<TD>45 , 001 </TD>
</TR>

<TR>
<TD>活期存款</TD>

<TD>台灣中小企業銀行</TD>

<TD>鄭貴蓮 </TD>

<TD/>

<TD>8, 178 </TD>
</TR>

<TR>
<TD>活期存款</TD>

<TD>世華聯合商業銀行</TD>

<TD>鄭貴蓮 </TD>

<TD/>

<TD>255 , 371 I </TD>
</TR>

<TR>
<TD>活期存款</TD>

<TD>第一商業銀行</TD>

<TD>鄭貴蓮</TD>

<TD/>

<TD>的加|</TD>
</TR>

<TR>
<TD>活期存款</TD>

<TD>土地銀行</TD>

<TD>鄭貴蓮 </TD>

<TD/>

<TD/>
</TR>
</Table>
<Figure>

<ImageData src=""/>
金額類幣JÍ'] 存放機相戶名折叫叫種值</Figure>

<P>九</P>

<P>監察院公報公職人員財產申報資料專刊第九二期 </P>

<P>一九三 </P>

<P>(六)外幣(指現金或旅行支票)(總價額:元) </P>

<P>折合新台幣價額</P>

<P>|幣別|所有人|金額</P>
</Sect>

<Sect>
<H3>|無\ \ </H3>

<P>nrH</P>

<P>Fhd phu AUU A44 AHu </P>

<P>(七)有價證券(股票，票券，債券a其他有價證券總價額:元)</P>

<P>1.股票(總價額: 649， 420元)</P>

<P>生 </P>

<Table>
<TR>
<TD>種類</TD>

<TD>所有</TD>

<TD>人</TD>

<TD>股</TD>

<TD>數</TD>

<TD>票面價額</TD>

<TD>總</TD>

<TD>額</TD>
</TR>

<TR>
<TD>大同</TD>

<TD>鄭貴蓮 </TD>

<TD/>

<TD/>

<TD>1, 934 </TD>

<TD>10 </TD>

<TD/>

<TD>19 , 340 </TD>
</TR>

<TR>
<TD>東元</TD>

<TD>鄭貴蓮 </TD>

<TD/>

<TD/>

<TD>4, 557 </TD>

<TD>10 </TD>

<TD/>

<TD>45 , 570 </TD>
</TR>

<TR>
<TD>福聚</TD>

<TD>鄭貴蓮 </TD>

<TD/>

<TD/>

<TD>1, 404 </TD>

<TD>10 </TD>

<TD/>

<TD>14 , 040 </TD>
</TR>

<TR>
<TD>太電</TD>

<TD>鄭貴蓮 </TD>

<TD/>

<TD/>

<TD>47 , 883 </TD>

<TD>10 </TD>

<TD/>

<TD>478 , 830 </TD>
</TR>

<TR>
<TD>嘉新</TD>

<TD>鄭貴蓮 </TD>

<TD/>

<TD/>

<TD>4, 764 </TD>

<TD>10 </TD>

<TD/>

<TD>47 , 640 </TD>
</TR>

<TR>
<TD>中鋼碳素</TD>

<TD>鄭貴蓮 </TD>

<TD/>

<TD/>

<TD>4, 400 </TD>

<TD>10 </TD>

<TD/>

<TD>44 , 000 </TD>
</TR>
</Table>

<P>2.票券(總價額:5， 000， 000元) </P>
<Figure>

<ImageData src=""/>
</Figure>

<P>種類所有票面價額總額</P>

<P>元富證券(註)鄭貴蓮10 5,000 ,000 </P>

<P>註:單位數 :500， 000;當中 400萬與友人共同持有。</P>

<P>Aaz--其一 </P>

<P>3.債券(總價額:元) </P>

<P>類有</P>
</Sect>

<Sect>
<H2>哩票面價額</H2>

<Sect>
<H3>種無</H3>

<P>,</P>

<P>..</P>

<P>:
</P>

<P>有一</P>

<P>券一證一</P>

<P>面貝一</P>

<P>AI.</P>

<P>‘、</P>

<P>JS</P>

<P>類lL!L有 單位數</P>

<P>， 4』『</P>

<P>總</P>

<P>他一</P>

<P>額「</P>

<P>聶貝一</P>

<P>元)</P>

<P>面市</P>
</Sect>
</Sect>

<Sect>
<H2>阿卡」</H2>

<P>E</P>

<P>產種類有人</P>

<P>元)務人及土包h上額 </P>

<P>3，500，000元)</P>

<P>額</P>

<P>晶貝</P>

<P>面</P>

<P>權及主也主止額</P>

<P>L竺人 </P>

<P>不動產抵押|余政憲彰化商業銀行股份有限公司岡山分行3,500 ,000 權設定高雄縣岡山鎮岡山路293號 」</P>

<P>J'</P>

<P>耕宏企業有限公司高雄縣橋頭鄉橋南路27號</P>

<Sect>
<H2>倆一責
</H2>

<P>‘、、-可</P>

<P>fk</P>

<P>4AA--Illi-</P>

<P>車頁-4</P>

<P>.. 
</P>

<P>一十一隨</P>

<P>-2</P>

<P>頁</P>

<P>余政憲</P>

<P>業一</P>

<Sect>
<H3>洋一人</H3>

<P>凡又一</P>

<P>一凡叉</P>

<P>他心一</P>

<P>-
</P>

<P>事 </P>

<P>8，000，000元)</P>

<P>臣工</P>

<P>IEt</P>

<P>業名稱及地址投資金額!露 </P>

<P>8,000,000 I 公</P>

<P>報</P>

<P>(十二)備註</P>

<P>鈕</P>

<P>此致
監察院
(受理申報機關〔構〕全稱)
</P>

<P>以上資料，本人係依法誠實申報，如有不實，願負法律責任。申報人:余政憲申報日期: 89年 12月 30日</P>

<P>公職人員財產申報資料專刊第九二期</P>

<P>九四</P>
</Sect>
</Sect>
</Sect>
</Part>
</TaggedPDF-doc>
