<?xml version="1.0" encoding="UTF-8" ?>
<!-- Created from PDF via Acrobat SaveAsXML -->
<!-- Mapping Table version: 28-February-2003 -->
<TaggedPDF-doc>
<?xpacket begin='﻿' id='W5M0MpCehiHzreSzNTczkc9d'?>
<?xpacket begin="﻿" id="W5M0MpCehiHzreSzNTczkc9d"?>
<x:xmpmeta xmlns:x="adobe:ns:meta/" x:xmptk="Adobe XMP Core 5.4-c005 78.147326, 2012/08/23-13:03:03        ">
   <rdf:RDF xmlns:rdf="http://www.w3.org/1999/02/22-rdf-syntax-ns#">
      <rdf:Description rdf:about=""
            xmlns:xmp="http://ns.adobe.com/xap/1.0/"
            xmlns:xmpMM="http://ns.adobe.com/xap/1.0/mm/"
            xmlns:dc="http://purl.org/dc/elements/1.1/"
            xmlns:pdf="http://ns.adobe.com/pdf/1.3/">
         <xmp:ModifyDate>2007-10-25T16:25:28+08:00</xmp:ModifyDate>
         <xmp:CreateDate>2007-10-25T16:25:24+08:00</xmp:CreateDate>
         <xmp:MetadataDate>2007-10-25T16:25:28+08:00</xmp:MetadataDate>
         <xmpMM:DocumentID>uuid:f9cd778b-3f73-4772-a473-6f9517b8b66b</xmpMM:DocumentID>
         <xmpMM:InstanceID>uuid:5488b1c2-45fd-471a-9021-9eaa085f156e</xmpMM:InstanceID>
         <dc:format>xml</dc:format>
         <pdf:Producer>Adobe Acrobat Pro 11.0.0 Paper Capture Plug-in</pdf:Producer>
      </rdf:Description>
   </rdf:RDF>
</x:xmpmeta>
                                                                                                    
                                                                                                    
                                                                                                    
                                                                                                    
                                                                                                    
                                                                                                    
                                                                                                    
                                                                                                    
                                                                                                    
                                                                                                    
                                                                                                    
                                                                                                    
                                                                                                    
                                                                                                    
                                                                                                    
                                                                                                    
                                                                                                    
                                                                                                    
                                                                                                    
                                                                                                    
                           
<?xpacket end="w"?>
<?xpacket end='r'?>

<P>公職</P>

<P>員財產申</P>

<P>報</P>

<P>表</P>

<P>人</P>

<P>缸</P>

<Table>
<TR>
<TH>申報人姓名</TH>

<TH>吳明洋</TH>

<TH>服務機關</TH>

<TH>l.高雄市政府</TH>

<TH/>

<TH>職稱 </TH>

<TH>1.局長</TH>

<TH/>
</TR>

<TR>
<TD>2. </TD>

<TD/>

<TD>2. </TD>

<TD/>
</TR>

<TR>
<TH>配偶</TH>

<TD>及未成年子</TD>

<TD>女</TD>

<TD>配偶及</TD>

<TD>未成</TD>

<TD>年子</TD>

<TD>女</TD>
</TR>

<TR>
<TH>稱</TH>

<TD>謂</TD>

<TD>姓</TD>

<TD>名</TD>

<TD>稱</TD>

<TD>謂</TD>

<TD>姓</TD>

<TD/>

<TD>名</TD>
</TR>

<TR>
<TH>妻</TH>

<TD/>

<TD>李貴娣</TD>

<TD/>

<TD>長子</TD>

<TD/>

<TD>吳行浩</TD>

<TD/>

<TD/>
</TR>
</Table>

<P>(一)不動產</P>

<P>l.土地</P>

<Table>
<TR>
<TD>土地坐落</TD>

<TD>面(平方公尺積) </TD>

<TD>權利範團(持分)</TD>

<TD>所有權人</TD>
</TR>

<TR>
<TD>台北市文山區萬陸段二小段。 115-0000地號 </TD>

<TD>202 </TD>

<TD>4分之l</TD>

<TD>李貴娣</TD>
</TR>

<TR>
<TD>高雄市新興區新興段二小段1241-0000地號 </TD>

<TD>3,137 </TD>

<TD>1000分之35</TD>

<TD>李貴娣</TD>
</TR>

<TR>
<TD>美pl國馬里G蘭ai州th，蓋澈bu斯rg堡，M， D(#9503 TIInstal l -ace , ers , 20879 , U S A) </TD>

<TD>86.61 </TD>

<TD>3分之l</TD>

<TD>李貴娣 </TD>
</TR>
</Table>

<P>2.房屋</P>

<Table>
<TR>
<TD>房屋標可可</TD>

<TD>(面平方公尺積) </TD>

<TD>權利範園(持分)</TD>

<TD>所有權人</TD>

<TD/>
</TR>

<TR>
<TD>台00北11市2-文000山建區號萬隆段二小段。 115-0000地號及 </TD>

<TD>125.82 </TD>

<TD>所有權全部</TD>

<TD>李貴娣</TD>

<TD/>
</TR>

<TR>
<TD>高00雄59市1-新00興O建區號新興段二小段1241-0000地號及 </TD>

<TD>90.42 </TD>

<TD>所有權全部</TD>

<TD>李貴娣</TD>
</TR>

<TR>
<TD>高00雄54市9-新00興O建區號新(興公段共二設小施段) 124l-OOOO地號及 </TD>

<TD>4,719.94 </TD>

<TD>1000分之38</TD>

<TD>李貴婦</TD>
</TR>

<TR>
<TD>美la國馬里Ga蘭it州he，蓋sb澈ur斯g，堡MD(#95037, TIInstal l F ce , Gaithersburg , MD , 20879 , U.S.A.) </TD>

<TD>166.50 </TD>

<TD>3分之l</TD>

<TD>李貴娣 </TD>

<TD/>
</TR>
</Table>

<P>籍</P>

<P>港</P>

<P>總類船數</P>

<P>齡川</P>

<P>有</P>

<P>噸</P>

<P>區
</P>

<P>六 一四</P>

<P>O</P>

<P>丌|i</P>

<P>Ta-</P>

<P>牌</P>

<P>↓且凡類</P>

<P>容</P>

<P>量</P>

<P>有</P>

<P>號碼</P>

<P>區
</P>

<P>照、</P>

<P>監察院公報公職人員財產申報資料專刊第二二期 </P>

<P>區空空
</P>

<P>式</P>

<P>製進廠J包幸存 |國籍標示及編號|所有</P>

<P>(五)存款(總金額:元)</P>

<P>1.新臺幣存款2,364 ,155 </P>

<P>監察院公報 公職人員財產申報資料專刊第二二期</P>

<Table>
<TR>
<TD>種類</TD>

<TD>存放機構</TD>

<TD>戶名</TD>

<TD>金</TD>

<TD>領</TD>
</TR>

<TR>
<TD>儲蓄存款</TD>

<TD>土銀</TD>

<TD>吳明洋 </TD>

<TD/>

<TD>327 ,543 </TD>
</TR>

<TR>
<TD>郵政儲金</TD>

<TD>郵局</TD>

<TD>吳明洋 </TD>

<TD/>

<TD>60 ,600 </TD>
</TR>

<TR>
<TD>郵政儲金</TD>

<TD>郵局</TD>

<TD>吳明洋 </TD>

<TD/>

<TD>304 ,050 </TD>
</TR>

<TR>
<TD>儲蓄存款</TD>

<TD>中國農民銀行</TD>

<TD>吳明洋 </TD>

<TD/>

<TD>183 ,000 </TD>
</TR>

<TR>
<TD>儲蓄存款</TD>

<TD>合庫</TD>

<TD>吳明洋 </TD>

<TD/>

<TD>131 ,122 </TD>
</TR>

<TR>
<TD>儲蓄存款</TD>

<TD>高雄銀行</TD>

<TD>吳明洋 </TD>

<TD/>

<TD>177 ,000 </TD>
</TR>
</Table>

<P>2.外幣及其他帶別存款</P>

<Table>
<TR>
<TH>種類</TH>

<TH>幣別</TH>

<TH>存放機構</TH>

<TH>戶名</TH>

<TH/>

<TH>金額</TH>
</TR>

<TR>
<TD/>

<TD>折合新臺幣價額</TD>
</TR>

<TR>
<TH>外歷支票存款</TH>

<TD>美金</TD>

<TD>美國運通銀行 </TD>

<TD>吳明洋 </TD>

<TD/>

<TD>15 ,061 </TD>
</TR>

<TR>
<TD/>

<TD>393 ,543 </TD>
</TR>

<TR>
<TH>外活期區支存票款~含</TH>

<TD>獎金 </TD>

<TD>First American Bank of Virginia(註) </TD>

<TD>吳明洋 </TD>

<TD/>

<TD>30 ,130 </TD>
</TR>

<TR>
<TD/>

<TD>787 ,297 </TD>
</TR>

<TR>
<TH>註: First American Bank of Virginia (Mclean , Virginia 22102 , U.S.A.) </TH>

<TD/>
</TR>
</Table>

<P>(六)外幣(指現金或旅行支票)(總價額:99 ,294 元) </P>

<P>瞥別所有人金額折合新臺幣價額</P>

<P>美金吳明洋3,800 99 ,294 </P>

<P>(七)有價證券(股票、票券、憤券及其他有價證券總價額:9,450 元)</P>

<P>1.股票(總價額: 9,450 元)</P>

<P>稜一叫
</P>

<P>六 一五</P>

<P>O</P>

<Table>
<TR>
<TD>種</TD>

<TD>類</TD>

<TD>所有人</TD>

<TD>股</TD>

<TD>數</TD>

<TD>票面價額</TD>

<TD>總</TD>

<TD>額!</TD>
</TR>

<TR>
<TD>中華紙漿</TD>

<TD/>

<TD>李貴娣 </TD>

<TD/>

<TD>150 </TD>

<TD>10 </TD>

<TD/>

<TD>1,500 I </TD>
</TR>

<TR>
<TD>聲賣股份</TD>

<TD/>

<TD>李貴娣 </TD>

<TD/>

<TD>2是5 </TD>

<TD>10 </TD>

<TD/>

<TD>2，鈞。</TD>
</TR>

<TR>
<TD>聯華電子</TD>

<TD/>

<TD>李貴娣 </TD>

<TD/>

<TD>550 </TD>

<TD>10 </TD>

<TD/>

<TD>~， 50_(l_j </TD>
</TR>
</Table>

<P>2.票券(總價頻:</P>

<P>類</P>

<P>持1 </P>

<P>.vp' </P>

<P>有票面價顏</P>

<P>人|單位數| </P>

<P>|| </P>

<P>3.債奉(總價頻:</P>

<P>有 票面價額</P>

<P>人|單位數l</P>

<P>也空
</P>

<P>種補一
</P>

<P>ω</P>

<P>4.其他有價詮奉(總價頻:</P>

<P>監察院公報</P>

<P>2崎一一
</P>

<P>一單一一</P>

<P>所無</P>

<P>有</P>

<P>人一一</P>

<P>空一其</P>

<Table>
<TR>
<TD>財產</TD>

<TD>種</TD>

<TD>報</TD>

<TD>所有</TD>

<TD>人</TD>

<TD>價</TD>

<TD>額</TD>
</TR>

<TR>
<TD>著作權(大學教材著作)</TD>

<TD/>

<TD/>

<TD>吳明洋 </TD>

<TD/>

<TD/>

<TD>100, 000 </TD>
</TR>

<TR>
<TD>珠寶</TD>

<TD/>

<TD/>

<TD>李貴娣 </TD>

<TD/>

<TD/>

<TD>180, 000 </TD>
</TR>
</Table>

<P>抵押權∞事業投資(總金頻:</P>

<P>權一一自一務債一一空一債</P>

<P>ω一種一欄一的
</P>

<P>元)</P>

<P>債</P>

<P>址</P>

<P>金</P>

<P>權</P>

<P>人</P>

<P>務人及地</P>

<P>元)</P>

<P>。。</P>

<P>1</P>

<P>數債務債權及地址金額</P>

<P>種 </P>

<P>人</P>

<P>人</P>

<P>土銀北市仁愛分行1, 800, 000</P>

<P>吳明洋</P>

<P>台北市仁愛路3段29號</P>

<P>元)</P>

<P>|投資人|投 實事業名稱及地址資金</P>

<P>|本欄空白 | </P>

<P>偈備註</P>

<Table>
<TR>
<TH>1)李貴娣所有坐落於台北市文山區萬隆段二小段。 115-0000地號持分之土地及建號。0112-000房</TH>
</TR>

<TR>
<TH>屋係於民國七十三年七月廿六日，因買賣取得。 </TH>
</TR>

<TR>
<TH>2)李貴娣所有坐落於高雄市新興區新興段二小段1241一0000地號持分之土地及建號00591一 000房</TH>
</TR>

<TR>
<TH>麗係於民國七十年十一月六日，因買賣而取得。 </TH>
</TR>

<TR>
<TH>3)美國馬里蘭州 (Gaithersburg， Tunstall Place， 9503號)土地及三層木架構房屋(連棟式</TH>
</TR>

<TR>
<TH>)係於民國八十二年六月贈買，總價美金106， 000元，與張征、吳佳宜等共三人出資合購。</TH>
</TR>
</Table>

<P>• 
</P>

<P>此致監察院</P>

<P>公職人員財產申報資料專刊</P>

<P>第二二期六。一六</P>

<P>(受理申報機關〔構〕全稱)</P>

<P>以上資料，本人係依法誠實申報，如有不實，顧負法律責任。</P>

<P>申報人:吳明洋申報日期: 84年1月 23日</P>

<P>監察院公報公職人員財產申報資料專刊第二二期六 一七</P>

<P>O</P>
</TaggedPDF-doc>
