<?xml version="1.0" encoding="UTF-8" ?>
<!-- Created from PDF via Acrobat SaveAsXML -->
<!-- Mapping Table version: 28-February-2003 -->
<TaggedPDF-doc>
<?xpacket begin='﻿' id='W5M0MpCehiHzreSzNTczkc9d'?>
<?xpacket begin="﻿" id="W5M0MpCehiHzreSzNTczkc9d"?>
<x:xmpmeta xmlns:x="adobe:ns:meta/" x:xmptk="Adobe XMP Core 5.4-c005 78.147326, 2012/08/23-13:03:03        ">
   <rdf:RDF xmlns:rdf="http://www.w3.org/1999/02/22-rdf-syntax-ns#">
      <rdf:Description rdf:about=""
            xmlns:xmp="http://ns.adobe.com/xap/1.0/"
            xmlns:dc="http://purl.org/dc/elements/1.1/"
            xmlns:xmpMM="http://ns.adobe.com/xap/1.0/mm/"
            xmlns:pdf="http://ns.adobe.com/pdf/1.3/">
         <xmp:ModifyDate>2007-11-05T15:29:45+08:00</xmp:ModifyDate>
         <xmp:CreateDate>2007-11-05T15:29:30+08:00</xmp:CreateDate>
         <xmp:MetadataDate>2007-11-05T15:29:45+08:00</xmp:MetadataDate>
         <xmp:CreatorTool>Adobe Acrobat 7.08</xmp:CreatorTool>
         <dc:format>xml</dc:format>
         <xmpMM:DocumentID>uuid:ca714f50-e46b-430e-befc-626ba5d06b13</xmpMM:DocumentID>
         <xmpMM:InstanceID>uuid:2f27a0cd-1fc3-4927-b7bf-d151ff50e70b</xmpMM:InstanceID>
         <pdf:Producer>Adobe Acrobat Pro 11.0.0 Paper Capture Plug-in</pdf:Producer>
      </rdf:Description>
   </rdf:RDF>
</x:xmpmeta>
                                                                                                    
                                                                                                    
                                                                                                    
                                                                                                    
                                                                                                    
                                                                                                    
                                                                                                    
                                                                                                    
                                                                                                    
                                                                                                    
                                                                                                    
                                                                                                    
                                                                                                    
                                                                                                    
                                                                                                    
                                                                                                    
                                                                                                    
                                                                                                    
                                                                                                    
                                                                                                    
                           
<?xpacket end="w"?>
<?xpacket end='r'?>

<P>公職</P>

<P>員</P>

<P>財產</P>

<P>申</P>

<P>報表</P>

<P>人</P>

<P>土地坐落面積權利範園(持分)所有權人(平方公尺)</P>

<Table>
<TR>
<TH>申報人姓名商己偶稱無</TH>

<TH>邱護瑩服務機關及未成年子謂姓</TH>

<TH>1.國民大會2. 女高己名稱</TH>

<TH>偶</TH>

<TH>及</TH>

<TH>1.國大代表職稱 2. 未成年子女謂姓名</TH>
</TR>
</Table>

<P>監察院公報公職人員財產申報資料專刊第三九期七四五</P>

<P>-O</P>

<P>(一)不動產</P>

<P>1.土地</P>

<P>無 </P>

<P>2.房屋</P>

<P>可言</P>

<P>房屋標面積 l權利範園(持分)所有權人</P>

<P>(平方公尺)</P>

<P>無</P>

<P>f
</P>

<P>港</P>

<P>汀， </P>

<P>-vr'P</P>

<P>有</P>

<P>噸</P>

<P>數</P>

<P>總</P>

<P>頁一</P>

<P>寸君步</P>

<P>船</P>

<P>籍</P>

<P>i 
</P>

<P>S R 2LZ</P>

<P>, </P>

<P>,'</P>

<P>牌</P>

<P>d生.</P>

<P>號司馬有</P>

<P>量</P>

<P>缸 </P>

<P>~、</P>

<P>司、</P>

<P>廿</P>

<P>鈕， </P>

<P>型式製造廠名幸存國籍標示及編號所有人無</P>

<P>(五)存款(總金額:19, 879, 835 元)</P>

<L>
<LI>
<Lbl>1.</Lbl>

<LBody>新臺幣存款 </LBody>
</LI>

<LI>
<Lbl>2.</Lbl>

<LBody>外幣及其他幣別存款</LBody>
</LI>
</L>

<Table>
<TR>
<TH>種</TH>

<TH>類</TH>

<TH>存放機構</TH>

<TH>尸名</TH>

<TH>金</TH>

<TH>額</TH>
</TR>

<TR>
<TD>定期存款</TD>

<TD/>

<TD>屏東一信</TD>

<TD>邱議瑩 </TD>

<TD/>

<TD>7, 400, 000 </TD>
</TR>

<TR>
<TD>活儲存款</TD>

<TD/>

<TD>屏東一信</TD>

<TD>邱議瑩 </TD>

<TD/>

<TD>75, 918 </TD>
</TR>

<TR>
<TD>定期存款</TD>

<TD/>

<TD>合庫</TD>

<TD>邱議瑩 </TD>

<TD/>

<TD>12, 000 , 000 </TD>
</TR>

<TR>
<TD>活儲存款</TD>

<TD>‘台東企銀</TD>

<TD>邱議瑩 </TD>

<TD/>

<TD>403, 917 </TD>
</TR>
</Table>

<P>金額</P>

<P>種類幣別存放機構戶名</P>

<P>折合新臺幣價額</P>

<P>無
(六)外幣(指現金或旅行支票)(總價額:元)
</P>

<P>|幣別|所有人|金額|折合新臺幣價額||無 I I </P>

<P>(七)有價證券(股票、票券、債券及其他有價證券總價頻:元)</P>

<P>1.股票(總價額:元)</P>

<P>種鈕叭</P>

<P>票面價額</P>

<P>類|所有人|股 </P>

<P>|| </P>

<P>2.票券(總價額:</P>

<P>有票面價額</P>

<P>生 人百</P>

<P>3.債券(總價額:</P>

<P>第三九期七四六</P>

<P>-O</P>

<P>種鈕川</P>

<P>有 票面價額</P>

<P>1 人巨型</P>

<P>4.其他有價證券(總價額:</P>

<P>的土
</P>

<P>有票面價額</P>

<P>區人哩</P>

<P>財產種類有</P>

<P>元)</P>

<P>權務人及地</P>

<P>金</P>

<P>址</P>

<P>收土</P>

<P>半斗
</P>

<P>元)務權人及地</P>

<P>金址</P>

<P>監察院公報公職人員財產申報資料專刊</P>

<P>臼事業投資(總金額:元)</P>

<P>|投資人|資事業名稱及地拖上,</P>

<P>4d1.凡足</P>

<P>投</P>

<P>資</P>

<P>金</P>

<P>監察院公報公職人員財產申報資料專刊</P>

<P>|無|</P>

<P>曲備註</P>

<P>無</P>

<P>ιny</P>

<P>致 </P>

<P>監察院</P>

<P>(受理申報機關 〔構〕全稱)</P>

<P>以上資料，本人係依法誠實申報，如有不實，願負法律責任。</P>

<P>申</P>

<P>報人:邱議瑩申報日期:85年8月 10日 </P>

<P>第三九期 七四七</P>

<P>-O</P>
</TaggedPDF-doc>
