<?xml version="1.0" encoding="UTF-8" ?>
<!-- Created from PDF via Acrobat SaveAsXML -->
<!-- Mapping Table version: 28-February-2003 -->
<TaggedPDF-doc>
<?xpacket begin='﻿' id='W5M0MpCehiHzreSzNTczkc9d'?>
<?xpacket begin="﻿" id="W5M0MpCehiHzreSzNTczkc9d"?>
<x:xmpmeta xmlns:x="adobe:ns:meta/" x:xmptk="Adobe XMP Core 5.4-c005 78.147326, 2012/08/23-13:03:03        ">
   <rdf:RDF xmlns:rdf="http://www.w3.org/1999/02/22-rdf-syntax-ns#">
      <rdf:Description rdf:about=""
            xmlns:xmp="http://ns.adobe.com/xap/1.0/"
            xmlns:dc="http://purl.org/dc/elements/1.1/"
            xmlns:xmpMM="http://ns.adobe.com/xap/1.0/mm/"
            xmlns:pdf="http://ns.adobe.com/pdf/1.3/">
         <xmp:ModifyDate>2007-11-05T15:52:11+08:00</xmp:ModifyDate>
         <xmp:CreateDate>2007-11-05T15:51:37+08:00</xmp:CreateDate>
         <xmp:MetadataDate>2007-11-05T15:52:11+08:00</xmp:MetadataDate>
         <xmp:CreatorTool>Adobe Acrobat 7.08</xmp:CreatorTool>
         <dc:format>xml</dc:format>
         <xmpMM:DocumentID>uuid:db35a1e8-1300-4908-9fe1-c4d5be0e83ee</xmpMM:DocumentID>
         <xmpMM:InstanceID>uuid:9d7d3050-bd7c-42f1-a764-f273d561d275</xmpMM:InstanceID>
         <pdf:Producer>Adobe Acrobat Pro 11.0.0 Paper Capture Plug-in</pdf:Producer>
      </rdf:Description>
   </rdf:RDF>
</x:xmpmeta>
                                                                                                    
                                                                                                    
                                                                                                    
                                                                                                    
                                                                                                    
                                                                                                    
                                                                                                    
                                                                                                    
                                                                                                    
                                                                                                    
                                                                                                    
                                                                                                    
                                                                                                    
                                                                                                    
                                                                                                    
                                                                                                    
                                                                                                    
                                                                                                    
                                                                                                    
                                                                                                    
                           
<?xpacket end="w"?>
<?xpacket end='r'?>

<P>公</P>

<P>職</P>

<P>員財產</P>

<P>申</P>

<P>報</P>

<P>表</P>

<P>人</P>

<P>1.土地</P>

<P>(一)不動產 權利範圍(持分)面積落地所有權人坐土3322 潘振球台北市大安區懷生段4小段271地號10000分之75,|尸房屋標示|拉L方」|叫圍(持揪枷W川 </P>

<P>(平方公尺)</P>

<P>2.房屋</P>

<P>分糾) 所有權人</P>

<P>|間真錯騙古臨騙區騙育蓋蠶鸝嘉驅2幣嘲琴勢?伊伊271地號蹦鯽27叫閃叫4叫州4</P>

<P>7叫咐 </P>

<Table>
<TR>
<TH>申報人姓名</TH>

<TH>潘振球</TH>

<TH>服務機關</TH>

<TH>1.國史館</TH>

<TH/>

<TH>職稱 </TH>

<TH>1.館長2.</TH>

<TH/>
</TR>

<TR>
<TD>2. </TD>

<TD/>
</TR>

<TR>
<TH>商己偶</TH>

<TD>及未成年子</TD>

<TD>女</TD>

<TD>商己偶及</TD>

<TD>未成年子</TD>

<TD>女</TD>
</TR>

<TR>
<TH>幸存</TH>

<TD>謂</TD>

<TD>姓</TD>

<TD>名</TD>

<TD>稱</TD>

<TD>謂</TD>

<TD>姓</TD>

<TD>名</TD>
</TR>

<TR>
<TH>妻</TH>

<TD/>

<TD>潘朱菊胎</TD>

<TD/>

<TD/>

<TD/>

<TD/>

<TD/>
</TR>
</Table>

<P>潘振球 </P>

<P>籍</P>

<P>港</P>

<P>停刊</P>

<P>、缸，</P>

<P>總類</P>

<P>噸</P>

<Part>
<H1>生</H1>

<P>有</P>
</Part>

<Part>
<H1>~ 
</H1>

<P>'去﹒</P>

<P>+ </P>

<P>量</P>

<P>牌</P>

<P>有</P>

<Sect>
<H1>生
</H1>

<P>號</P>

<P>互為</P>

<P>缸</P>
</Sect>

<Sect>
<H1>區
</H1>

<P>J.m、</P>

<P>型式製造廠名稱國籍標示及編號所有人無</P>

<P>(五)存款(總金額:12 ,952 ,008.29 元)</P>

<P>1.新臺幣存款</P>

<Table>
<TR>
<TH>種類</TH>

<TH>存放機構</TH>

<TH>戶名</TH>

<TH>金</TH>

<TH>額</TH>
</TR>

<TR>
<TD>定期存款</TD>

<TD>台銀</TD>

<TD>潘接球 </TD>

<TD/>

<TD>1,878 ,500 </TD>
</TR>

<TR>
<TD>定期存款</TD>

<TD>台銀</TD>

<TD>潘朱菊胎 </TD>

<TD/>

<TD>428 ,064 </TD>
</TR>

<TR>
<TD>郵政定期</TD>

<TD>郵局</TD>

<TD>潘振球 </TD>

<TD/>

<TD>1,000 ,000 </TD>
</TR>

<TR>
<TD>郵政定期</TD>

<TD>郵局</TD>

<TD>潘朱菊胎 </TD>

<TD/>

<TD>1,500 ,000 </TD>
</TR>

<TR>
<TD>郵政定期</TD>

<TD>郵局</TD>

<TD>潘朱菊胎 </TD>

<TD/>

<TD>7祉，314 </TD>
</TR>
</Table>

<P>監察院公報公職人員財產申報資料專刊第四四期</P>

<P>一二二四三</P>

<Table>
<TR>
<TD>定期存款</TD>

<TD>台灣省合作金庫</TD>

<TD>潘朱菊胎 </TD>

<TD>1,000 ,000 </TD>
</TR>

<TR>
<TD>定期存款</TD>

<TD>台灣省合作金庫</TD>

<TD>潘朱菊胎 </TD>

<TD>560 ,000 </TD>
</TR>

<TR>
<TD>定期存款</TD>

<TD>台灣省合作金庫</TD>

<TD>潘朱菊胎 </TD>

<TD>300 ,000 </TD>
</TR>

<TR>
<TD>定期存款</TD>

<TD>合作金庫</TD>

<TD>潘朱菊胎 </TD>

<TD>695 ,894 </TD>
</TR>

<TR>
<TD>定期存款</TD>

<TD>合作金庫</TD>

<TD>潘朱菊胎 </TD>

<TD>800 ,000 </TD>
</TR>

<TR>
<TD>郵政活期</TD>

<TD>郵局</TD>

<TD>潘振球 </TD>

<TD>1,038 , 188 </TD>
</TR>

<TR>
<TD>郵政劃撥</TD>

<TD>郵局</TD>

<TD>潘振球 </TD>

<TD>676 </TD>
</TR>

<TR>
<TD>活期</TD>

<TD>台銀</TD>

<TD>潘振球 </TD>

<TD>344 , 193 </TD>
</TR>

<TR>
<TD>活期</TD>

<TD>台銀</TD>

<TD>潘朱菊胎 </TD>

<TD>179， 41是 .29</TD>
</TR>

<TR>
<TD>活期</TD>

<TD>合作金庫</TD>

<TD>潘朱菊胎 </TD>

<TD>379 ,244 </TD>
</TR>

<TR>
<TD>郵政活期</TD>

<TD>郵局</TD>

<TD>潘朱菊胎 </TD>

<TD>774 ,941 </TD>
</TR>

<TR>
<TD>定存</TD>

<TD>台銀</TD>

<TD>潘朱菊胎 </TD>

<TD>831 ,600 </TD>
</TR>
</Table>

<P>2.外幣及其他幣別存款</P>

<Table>
<TR>
<TH>種類</TH>

<TH>幣 )J11 </TH>

<TH>存放機構</TH>

<TH>戶名</TH>

<TH>金額</TH>
</TR>

<TR>
<TD>折合新臺幣價額 </TD>
</TR>

<TR>
<TH/>

<TD/>

<TD/>

<TD/>

<TD>18 ,072 </TD>
</TR>

<TR>
<TH>定存 </TH>

<TD>USD </TD>

<TD>合作金庫</TD>

<TD>潘朱菊胎 </TD>

<TD>496 ,980 </TD>
</TR>
</Table>

<P>(六)外幣(指現，金或旅行支票)(總價額:55 ,000 元) </P>

<P>幣別所有人金額折合新臺幣價額</P>

<P>美金潘振球2,000 55 ,000 </P>

<P>(七)有價證奉(股票、票券、債券及其他有價證券總價額:元)</P>

<P>1.股票(總價額:元)</P>

<P>票面價額</P>

<P>類|所有人|波 </P>

<Sect>
<H2>|| 
</H2>

<P>2.票券(總價額;元)</P>

<P>種無</P>
</Sect>

<Sect>
<H1>圳工州工
</H1>

<P>有</P>
</Sect>

<Sect>
<H1>人自</H1>

<P>3.債券(總價額:元)</P>

<P>有</P>

<Sect>
<H1>人 I~~.I </H1>

<P>司立 
</P>

<P>監察院公報公職人員財產申報資料專刊第四四期 一二二四四</P>

<P>總額</P>

<P>面貝面管一恥 </P>

<P>4.其他有價證券(總價額:</P>

<P>， </P>

<P>監察院公報公職人員財產申報資料專刊</P>

<P>第四四期一二二四五</P>

<P>E'</P>

<P>--bd</P>

<P>、‘ </P>

<Table>
<TR>
<TD>產</TD>

<TD/>

<TD/>

<TD>種</TD>

<TD/>

<TD>元)</TD>

<TD>類</TD>

<TD/>

<TD>有</TD>

<TD>半斗</TD>
</TR>

<TR>
<TD>權</TD>

<TD>人</TD>

<TD>債</TD>

<TD/>

<TD>務</TD>

<TD>人</TD>

<TD/>

<TD>及</TD>

<TD>地</TD>

<TD>金址</TD>
</TR>

<TR>
<TD>務</TD>

<TD>人資</TD>

<TD>債事</TD>

<TD/>

<TD>權業</TD>

<TD>元)人元)名</TD>

<TD>稱</TD>

<TD>及及</TD>

<TD>地地</TD>

<TD>世|斗址</TD>
</TR>
</Table>

<P>1</P>

<P>元一持一</P>

<P>-Y缸，</P>

<P>一單一一</P>

<P>類</P>

<P>時川，</P>

<P>人一一</P>

<P>有</P>

<P>、 </P>

<P>-E</P>

<P>實金</P>

<P>投</P>

<P>無</P>

<P>此致監察院</P>

<P>(受理申報機關〔構〕全稱)</P>

<P>以上資料，本人係依法誠實申報，如有不實，願負法律責任。</P>

<P>申報人:潘振球申報日期: 85年 12月 24日</P>
</Sect>
</Sect>
</Sect>
</Part>
</TaggedPDF-doc>
