<?xml version="1.0" encoding="UTF-8" ?>
<!-- Created from PDF via Acrobat SaveAsXML -->
<!-- Mapping Table version: 28-February-2003 -->
<TaggedPDF-doc>
<?xpacket begin='﻿' id='W5M0MpCehiHzreSzNTczkc9d'?>
<?xpacket begin="﻿" id="W5M0MpCehiHzreSzNTczkc9d"?>
<x:xmpmeta xmlns:x="adobe:ns:meta/" x:xmptk="Adobe XMP Core 5.4-c005 78.147326, 2012/08/23-13:03:03        ">
   <rdf:RDF xmlns:rdf="http://www.w3.org/1999/02/22-rdf-syntax-ns#">
      <rdf:Description rdf:about=""
            xmlns:xmp="http://ns.adobe.com/xap/1.0/"
            xmlns:dc="http://purl.org/dc/elements/1.1/"
            xmlns:xmpMM="http://ns.adobe.com/xap/1.0/mm/"
            xmlns:pdf="http://ns.adobe.com/pdf/1.3/">
         <xmp:ModifyDate>2007-11-12T11:50+08:00</xmp:ModifyDate>
         <xmp:CreateDate>2007-11-12T11:49:43+08:00</xmp:CreateDate>
         <xmp:MetadataDate>2007-11-12T11:50+08:00</xmp:MetadataDate>
         <xmp:CreatorTool>Adobe Acrobat 7.08</xmp:CreatorTool>
         <dc:format>xml</dc:format>
         <xmpMM:DocumentID>uuid:0dd92155-e398-44f4-a0cc-b6daa951f083</xmpMM:DocumentID>
         <xmpMM:InstanceID>uuid:e6c3e049-6397-4ce0-b9c9-cedef38d3fd9</xmpMM:InstanceID>
         <pdf:Producer>Adobe Acrobat Pro 11.0.0 Paper Capture Plug-in</pdf:Producer>
      </rdf:Description>
   </rdf:RDF>
</x:xmpmeta>
                                                                                                    
                                                                                                    
                                                                                                    
                                                                                                    
                                                                                                    
                                                                                                    
                                                                                                    
                                                                                                    
                                                                                                    
                                                                                                    
                                                                                                    
                                                                                                    
                                                                                                    
                                                                                                    
                                                                                                    
                                                                                                    
                                                                                                    
                                                                                                    
                                                                                                    
                                                                                                    
                           
<?xpacket end="w"?>
<?xpacket end='r'?>

<P>公職</P>

<P>員財產申</P>

<P>報表</P>

<P>人</P>

<P>1,998cc JW8889 </P>

<Table>
<TR>
<TH>申報人姓名</TH>

<TH>張蔡美</TH>

<TH>服務機關</TH>

<TH>l.台灣省議會 </TH>

<TH/>

<TH>職稱 </TH>

<TH>1.議員2.</TH>

<TH><Figure>

<ImageData src=""/>
</Figure>
</TH>
</TR>

<TR>
<TD>2. </TD>

<TD/>
</TR>

<TR>
<TH>商已偶</TH>

<TD>及未成年子</TD>

<TD>女</TD>

<TD>配偽及</TD>

<TD>未成年子</TD>

<TD>女</TD>
</TR>

<TR>
<TH>稱</TH>

<TD>謂</TD>

<TD>姓</TD>

<TD>名</TD>

<TD>稱</TD>

<TD>謂</TD>

<TD>姓</TD>

<TD>名</TD>
</TR>

<TR>
<TH>夫</TH>

<TD/>

<TD>張漢強</TD>

<TD/>

<TD/>

<TD/>

<TD/>

<TD/>
</TR>
</Table>

<P>(一)不動產</P>

<P>l.土地</P>

<Table>
<TR>
<TD>土地</TD>

<TD>坐</TD>

<TD>落</TD>

<TD>(面平方公尺積) </TD>

<TD>權利範園(持分)</TD>

<TD>所有權人 l</TD>
</TR>

<TR>
<TD>新竹市民富段596地號 </TD>

<TD/>

<TD/>

<TD>89 </TD>

<TD>所有權全部</TD>

<TD>張漢強</TD>
</TR>

<TR>
<TD>新竹市民富段596-1地號 </TD>

<TD/>

<TD/>

<TD>0.50 </TD>

<TD>所有權全部</TD>

<TD>張漠強</TD>
</TR>

<TR>
<TD>新竹市東光段518-10地號 </TD>

<TD/>

<TD/>

<TD>122 </TD>

<TD>所有權全部</TD>

<TD>張蔡美</TD>
</TR>
</Table>

<P>2.房屋</P>

<Table>
<TR>
<TD>房屋標可言</TD>

<TD>面(平方公尺積) </TD>

<TD>權利範園(持分)</TD>

<TD>所有權人</TD>
</TR>

<TR>
<TD>新弄竹21號市民)(三富層段5共96)地號(新竹市西大路780巷46 </TD>

<TD>133.28 </TD>

<TD>所有權全部</TD>

<TD>張漢強</TD>
</TR>

<TR>
<TD>新口號竹市)(東四層光共段5) 18-lO地號(新竹市八德路9巷 </TD>

<TD>259.92 </TD>

<TD>所有權全部</TD>

<TD>張蔡美</TD>
</TR>
</Table>

<P>..</P>

<P>弘一種一無一但</P>

<P>種小自客(四)航空器</P>

<P>、</P>

<P>拍一車</P>

<P>船一汽</P>

<P>'，-、‘'，'，</P>

<P>港</P>

<P>總類</P>

<P>教汽</P>

<P>船數</P>

<P>所</P>

<P>籍</P>

<P>有</P>

<P>頓</P>

<P>'忌，</P>

<P>有</P>

<P>牌照號碼</P>

<P>缸</P>

<P>量</P>

<P>所</P>

<P>人</P>

<P>。</P>

<P>張蔡美 </P>

<P>可</P>

<P>|型式|製造廠名稱|國籍標示及編號|所有</P>

<P>|無|</P>

<P>(五)存款(總金額: 2,281 ,626.60 元) </P>

<P>1.新臺幣存款</P>

<P>AA</P>

<P>監察院公報公職人員財產申報資料專刊第八三期 </P>

<P>一八八</P>

<P>存一萬類</P>

<P>儲活種有</P>

<P>-通</P>

<P>銀行</P>

<P>放機</P>

<Part>
<H1>半斗
</H1>

<P>額的 </P>

<P>可</P>

<P>nhu </P>

<P>EEA</P>

<P>叮/心</P>

<P>監察院公報公職人員財產申報資料專刊第八三期</P>

<P>一八九</P>

<Table>
<TR>
<TD>合活儲</TD>

<TD>萬通銀行</TD>

<TD>張蔡美 </TD>

<TD>1,041 </TD>
</TR>

<TR>
<TD>有活儲</TD>

<TD>台灣銀行</TD>

<TD>張蔡美 </TD>

<TD>170 ,232 </TD>
</TR>

<TR>
<TD>有活儲</TD>

<TD>新竹市第一信用合作社</TD>

<TD>張蔡美 </TD>

<TD>916 ,364 </TD>
</TR>

<TR>
<TD>有活儲</TD>

<TD>新竹市第五信用合作社</TD>

<TD>張蔡美 </TD>

<TD>87 ,497.60 </TD>
</TR>

<TR>
<TD>有活儲</TD>

<TD>新竹市第五信用合作社</TD>

<TD>張蔡美 </TD>

<TD>693 ,847 1 </TD>
</TR>

<TR>
<TD>有項目資料係申報人於88年8月 10日依法補正部份 </TD>

<TD/>

<TD/>
</TR>
</Table>

<P>2.外幣及其他瞥別存款</P>

<P>種</P>

<P>類i瞥
</P>

<P>&gt;}Ij 存放機構</P>

<P>、尸</P>

<P>金</P>

<P>名</P>

<P>|無 I I </P>

<P>(六)外幣(指現金或旅行支票)(總價額:元)</P>

<P>自阿</P>

<P>|幣別|所有人|金額|折合新臺幣價額|</P>

<P>|無 I . I </P>

<P>(七)有價證券(股票、票券、債券及其他有價證?總價額:元)</P>

<P>1.股票(總價額:</P>

<P>票面價額</P>

<P>類|所有人|股 </P>

<P>|| </P>

<P>2.票券(總價額:</P>

<P>l </P>

<P>p</P>

<P>拉，</P>

<P>|種</P>

<P>所</P>

<P>有</P>
</Part>

<Part>
<H1>人用
</H1>

<P>|無 </P>

<P>3.債券(總價額:</P>

<P>人吾
</P>

<P>類</P>

<P>伽'，</P>

<P>-V</P>

<P>呼叫</P>

<P>1 </P>

<P>有</P>

<P>4.其他有價證券(總價額:</P>

<P>恃且已伙同店已
</P>

<P>有</P>

<P>人曾</P>

<P>所類</P>

<P>產一</P>

<P>財一他一其一</P>

<P>產種類</P>

<P>有</P>

<P>價人</P>

<P>(九)債權(總金額:元)</P>

<P>|種類|債權</P>

<P>人</P>

<P>債</P>

<P>務人及地</P>

<P>址</P>

<P>金</P>

<P>|無|</P>

<P>Fhd nHu nHU nuu</P>

<P>nHV nHU </P>

<P>(十)債務(總金額:元)</P>

<P>6</P>

<Table>
<TR>
<TD>種類</TD>

<TD>債務人</TD>

<TD>債權人及</TD>

<TD>地</TD>

<TD>拖上</TD>

<TD>金</TD>

<TD>額</TD>
</TR>

<TR>
<TD>私人借款</TD>

<TD>張蔡美</TD>

<TD>劉美大國為德洲歐文市茉兒街 1024 </TD>

<TD/>

<TD/>

<TD/>

<TD>5,000 ,000 </TD>
</TR>

<TR>
<TD>有房屋祇押</TD>

<TD>張蔡美</TD>

<TD>台灣土地銀行 </TD>

<TD/>

<TD/>

<TD/>

<TD>1,500 , 000 </TD>
</TR>

<TR>
<TD>有項目資料係申報人於88年8月 10日依法補正部份</TD>

<TD/>

<TD/>

<TD/>

<TD/>
</TR>
</Table>

<Table>
<TR>
<TH>t母事業投資(總金額:</TH>

<TH/>

<TH/>

<TH/>

<TH>元)</TH>
</TR>

<TR>
<TH>|投資人|</TH>

<TD>投</TD>

<TD>資 </TD>

<TD>事</TD>

<TD>業</TD>

<TD>名</TD>

<TD>稱</TD>

<TD>及</TD>

<TD>地</TD>

<TD>拖上</TD>

<TD>資</TD>

<TD>金</TD>
</TR>

<TR>
<TH>|無|</TH>

<TD/>

<TD/>

<TD/>

<TD/>

<TD/>

<TD/>

<TD/>

<TD/>

<TD/>

<TD/>
</TR>

<TR>
<TH>的備註</TH>

<TD/>

<TD/>

<TD/>

<TD/>

<TD/>

<TD/>

<TD/>

<TD/>

<TD/>

<TD/>
</TR>
</Table>

<P>無</P>

<P>此致監察院</P>

<P>(受理申報機關〔構〕全稱)以上資料，本人係依法誠實申報，如有不實，顧負法律責任。</P>

<P>申</P>

<P>報人:張蔡美申報日期: 86年 12月 14日</P>

<P>監察院公報公職人員財產申報資料專刊第八三期一九</P>

<P>O</P>
</Part>
</TaggedPDF-doc>
